{
  "data": [
    {
      "LGJCPENNFBC": 3001,
      "BKCIGACKEFD": 1,
      "INGADDMLLEB": 31101,
      "JAIGONLNLEE": [
        0
      ],
      "ABDDIFGMCPL": [
        0
      ]
    },
    {
      "LGJCPENNFBC": 3002,
      "BKCIGACKEFD": 1,
      "INGADDMLLEB": 31102,
      "JAIGONLNLEE": [
        0
      ],
      "ABDDIFGMCPL": [
        0
      ]
    },
    {
      "LGJCPENNFBC": 3003,
      "BKCIGACKEFD": 1,
      "INGADDMLLEB": 31103,
      "JAIGONLNLEE": [
        0
      ],
      "ABDDIFGMCPL": [
        0
      ]
    },
    {
      "LGJCPENNFBC": 3004,
      "BKCIGACKEFD": 1,
      "INGADDMLLEB": 31104,
      "JAIGONLNLEE": [
        0
      ],
      "ABDDIFGMCPL": [
        0
      ]
    }
  ]
}