{
  "data": [
    {
      "LGJCPENNFBC": 1,
      "BKCIGACKEFD": 1,
      "DMGFKMJNIPF": {
        "2": 200,
        "8000": 20
      },
      "HBJAHCGKJJD": {
        "DOHLNDIPHAJ": "3112"
      },
      "GFMDILIKGLM": {
        "DOHLNDIPHAJ": "3057"
      },
      "ALGGJBJOLMO": 400,
      "CGFMAIFHLEO": 1
    },
    {
      "LGJCPENNFBC": 2,
      "BKCIGACKEFD": 1,
      "DMGFKMJNIPF": {
        "2": 200,
        "8000": 20
      },
      "BJKCACPPLGN": "4015",
      "HBJAHCGKJJD": {
        "DOHLNDIPHAJ": "4843"
      },
      "GFMDILIKGLM": {
        "DOHLNDIPHAJ": "4844"
      },
      "ALGGJBJOLMO": 750,
      "CGFMAIFHLEO": 1
    },
    {
      "LGJCPENNFBC": 3,
      "BKCIGACKEFD": 1,
      "DMGFKMJNIPF": {
        "2": 200,
        "8000": 20
      },
      "BJKCACPPLGN": "1000",
      "HBJAHCGKJJD": {
        "DOHLNDIPHAJ": "4847"
      },
      "GFMDILIKGLM": {
        "DOHLNDIPHAJ": "4848"
      },
      "ALGGJBJOLMO": 2,
      "CGFMAIFHLEO": 60
    },
    {
      "LGJCPENNFBC": 4,
      "BKCIGACKEFD": 1,
      "DMGFKMJNIPF": {
        "2": 200,
        "8000": 20
      },
      "BJKCACPPLGN": "1000",
      "HBJAHCGKJJD": {
        "DOHLNDIPHAJ": "4849"
      },
      "GFMDILIKGLM": {
        "DOHLNDIPHAJ": "4850"
      },
      "ALGGJBJOLMO": 2,
      "CGFMAIFHLEO": 120
    },
    {
      "LGJCPENNFBC": 5,
      "BKCIGACKEFD": 1,
      "DMGFKMJNIPF": {
        "2": 200,
        "8000": 10
      },
      "BJKCACPPLGN": "1098",
      "HBJAHCGKJJD": {
        "DOHLNDIPHAJ": "4851"
      },
      "GFMDILIKGLM": {
        "DOHLNDIPHAJ": "4852"
      },
      "ALGGJBJOLMO": 209,
      "CGFMAIFHLEO": 1,
      "DKEIDHDHLMC": 10998
    },
    {
      "LGJCPENNFBC": 6,
      "BKCIGACKEFD": 1,
      "DMGFKMJNIPF": {
        "2": 200,
        "8000": 10
      },
      "BJKCACPPLGN": "1099",
      "HBJAHCGKJJD": {
        "DOHLNDIPHAJ": "4853"
      },
      "GFMDILIKGLM": {
        "DOHLNDIPHAJ": "4924"
      },
      "ALGGJBJOLMO": 210,
      "CGFMAIFHLEO": 1,
      "DKEIDHDHLMC": 10999
    },
    {
      "LGJCPENNFBC": 7,
      "BKCIGACKEFD": 1,
      "DMGFKMJNIPF": {
        "2": 200,
        "8000": 10
      },
      "BJKCACPPLGN": "3801",
      "HBJAHCGKJJD": {
        "DOHLNDIPHAJ": "4925"
      },
      "GFMDILIKGLM": {
        "DOHLNDIPHAJ": "4926"
      },
      "ALGGJBJOLMO": 201,
      "CGFMAIFHLEO": 2,
      "DKEIDHDHLMC": 11012
    },
    {
      "LGJCPENNFBC": 8,
      "BKCIGACKEFD": 1,
      "DMGFKMJNIPF": {
        "2": 200,
        "8000": 10
      },
      "BJKCACPPLGN": "2",
      "HBJAHCGKJJD": {
        "DOHLNDIPHAJ": "4927"
      },
      "GFMDILIKGLM": {
        "DOHLNDIPHAJ": "4928"
      },
      "ALGGJBJOLMO": 407,
      "CGFMAIFHLEO": 1
    },
    {
      "LGJCPENNFBC": 9,
      "BKCIGACKEFD": 1,
      "DMGFKMJNIPF": {
        "2": 200,
        "8000": 10
      },
      "BJKCACPPLGN": "4015",
      "HBJAHCGKJJD": {
        "DOHLNDIPHAJ": "4929"
      },
      "GFMDILIKGLM": {
        "DOHLNDIPHAJ": "4930"
      },
      "ALGGJBJOLMO": 1303,
      "CGFMAIFHLEO": 5
    }
  ]
}