{
  "data": [
    {
      "LGJCPENNFBC": 801001,
      "BKCIGACKEFD": 1,
      "OIJIAGICBCI": [
        5,
        35,
        60
      ],
      "LBBONFCMFAL": [
        3,
        999,
        999
      ],
      "JJFDLLLBOBM": {
        "OBLDLILOOGO": [
          800001,
          1
        ],
        "NKGEDIMKJHL": [
          250,
          100
        ]
      },
      "FBELMLMIEED": {
        "OBLDLILOOGO": [
          800001,
          2
        ],
        "NKGEDIMKJHL": [
          250,
          2000
        ]
      },
      "PACFFMKGFAO": {
        "OBLDLILOOGO": [
          800001,
          2
        ],
        "NKGEDIMKJHL": [
          200,
          1000
        ]
      },
      "DJGELAEPLOM": 2,
      "HBJAHCGKJJD": {
        "DOHLNDIPHAJ": "1697"
      },
      "MEGDMLJGGKJ": {
        "DOHLNDIPHAJ": "1698"
      },
      "LMDJKJCPJHF": {
        "DOHLNDIPHAJ": "1699"
      },
      "DNHAGPFHGCE": "Item_Icon_Supply_Dairy_1",
      "LKLEEPGOHLG": 801001,
      "BDPAGGCLONI": 7
    },
    {
      "LGJCPENNFBC": 801002,
      "BKCIGACKEFD": 1,
      "OIJIAGICBCI": [
        5,
        35,
        60
      ],
      "LBBONFCMFAL": [
        3,
        999,
        999
      ],
      "JJFDLLLBOBM": {
        "OBLDLILOOGO": [
          800001,
          1
        ],
        "NKGEDIMKJHL": [
          325,
          100
        ]
      },
      "FBELMLMIEED": {
        "OBLDLILOOGO": [
          800001,
          2
        ],
        "NKGEDIMKJHL": [
          325,
          2250
        ]
      },
      "PACFFMKGFAO": {
        "OBLDLILOOGO": [
          800001,
          2
        ],
        "NKGEDIMKJHL": [
          250,
          1500
        ]
      },
      "DJGELAEPLOM": 2,
      "HBJAHCGKJJD": {
        "DOHLNDIPHAJ": "1700"
      },
      "MEGDMLJGGKJ": {
        "DOHLNDIPHAJ": "1698"
      },
      "LMDJKJCPJHF": {
        "DOHLNDIPHAJ": "1701"
      },
      "DNHAGPFHGCE": "Item_Icon_Supply_Dairy_2",
      "LKLEEPGOHLG": 801002,
      "BDPAGGCLONI": 7
    },
    {
      "LGJCPENNFBC": 801003,
      "BKCIGACKEFD": 1,
      "OIJIAGICBCI": [
        5,
        35,
        60
      ],
      "LBBONFCMFAL": [
        3,
        999,
        999
      ],
      "JJFDLLLBOBM": {
        "OBLDLILOOGO": [
          800001,
          1
        ],
        "NKGEDIMKJHL": [
          400,
          100
        ]
      },
      "FBELMLMIEED": {
        "OBLDLILOOGO": [
          800001,
          2
        ],
        "NKGEDIMKJHL": [
          400,
          3000
        ]
      },
      "PACFFMKGFAO": {
        "OBLDLILOOGO": [
          800001,
          2
        ],
        "NKGEDIMKJHL": [
          300,
          2000
        ]
      },
      "DJGELAEPLOM": 2,
      "HBJAHCGKJJD": {
        "DOHLNDIPHAJ": "1702"
      },
      "MEGDMLJGGKJ": {
        "DOHLNDIPHAJ": "1698"
      },
      "LMDJKJCPJHF": {
        "DOHLNDIPHAJ": "1703"
      },
      "DNHAGPFHGCE": "Item_Icon_Supply_Dairy_3",
      "LKLEEPGOHLG": 801003,
      "BDPAGGCLONI": 7
    },
    {
      "LGJCPENNFBC": 801004,
      "BKCIGACKEFD": 1,
      "OIJIAGICBCI": [
        5,
        35,
        60
      ],
      "LBBONFCMFAL": [
        3,
        999,
        999
      ],
      "JJFDLLLBOBM": {
        "OBLDLILOOGO": [
          800001,
          1
        ],
        "NKGEDIMKJHL": [
          475,
          100
        ]
      },
      "FBELMLMIEED": {
        "OBLDLILOOGO": [
          800001,
          2
        ],
        "NKGEDIMKJHL": [
          475,
          3750
        ]
      },
      "PACFFMKGFAO": {
        "OBLDLILOOGO": [
          800001,
          2
        ],
        "NKGEDIMKJHL": [
          350,
          2500
        ]
      },
      "DJGELAEPLOM": 2,
      "HBJAHCGKJJD": {
        "DOHLNDIPHAJ": "1704"
      },
      "MEGDMLJGGKJ": {
        "DOHLNDIPHAJ": "1698"
      },
      "LMDJKJCPJHF": {
        "DOHLNDIPHAJ": "1705"
      },
      "DNHAGPFHGCE": "Item_Icon_Supply_Dairy_4",
      "LKLEEPGOHLG": 801004,
      "BDPAGGCLONI": 7
    },
    {
      "LGJCPENNFBC": 801005,
      "BKCIGACKEFD": 1,
      "OIJIAGICBCI": [
        5,
        35,
        60
      ],
      "LBBONFCMFAL": [
        3,
        999,
        999
      ],
      "JJFDLLLBOBM": {
        "OBLDLILOOGO": [
          800001,
          1
        ],
        "NKGEDIMKJHL": [
          550,
          100
        ]
      },
      "FBELMLMIEED": {
        "OBLDLILOOGO": [
          800001,
          2
        ],
        "NKGEDIMKJHL": [
          550,
          4500
        ]
      },
      "PACFFMKGFAO": {
        "OBLDLILOOGO": [
          800001,
          2
        ],
        "NKGEDIMKJHL": [
          400,
          3000
        ]
      },
      "DJGELAEPLOM": 2,
      "HBJAHCGKJJD": {
        "DOHLNDIPHAJ": "1706"
      },
      "MEGDMLJGGKJ": {
        "DOHLNDIPHAJ": "1698"
      },
      "LMDJKJCPJHF": {
        "DOHLNDIPHAJ": "1707"
      },
      "DNHAGPFHGCE": "Item_Icon_Supply_Dairy_5",
      "LKLEEPGOHLG": 801005,
      "BDPAGGCLONI": 7
    },
    {
      "LGJCPENNFBC": 802001,
      "BKCIGACKEFD": 2,
      "OIJIAGICBCI": [
        5,
        20,
        75
      ],
      "LBBONFCMFAL": [
        3,
        3,
        999
      ],
      "JJFDLLLBOBM": {
        "OBLDLILOOGO": [
          800001,
          1
        ],
        "NKGEDIMKJHL": [
          400,
          100
        ]
      },
      "FBELMLMIEED": {
        "OBLDLILOOGO": [
          800001,
          9010
        ],
        "NKGEDIMKJHL": [
          400,
          5
        ]
      },
      "PACFFMKGFAO": {
        "OBLDLILOOGO": [
          800001,
          9009
        ],
        "NKGEDIMKJHL": [
          300,
          5
        ]
      },
      "DJGELAEPLOM": 2,
      "HBJAHCGKJJD": {
        "DOHLNDIPHAJ": "1667"
      },
      "MEGDMLJGGKJ": {
        "DOHLNDIPHAJ": "1668"
      },
      "LMDJKJCPJHF": {
        "DOHLNDIPHAJ": "1669"
      },
      "DNHAGPFHGCE": "Item_Icon_Supply_Dairy_6",
      "LKLEEPGOHLG": 802001,
      "BDPAGGCLONI": 7
    },
    {
      "LGJCPENNFBC": 802002,
      "BKCIGACKEFD": 2,
      "OIJIAGICBCI": [
        5,
        15,
        80
      ],
      "LBBONFCMFAL": [
        3,
        999,
        999
      ],
      "JJFDLLLBOBM": {
        "OBLDLILOOGO": [
          1,
          2
        ],
        "NKGEDIMKJHL": [
          200,
          200
        ]
      },
      "FBELMLMIEED": {
        "OBLDLILOOGO": [
          1,
          2
        ],
        "NKGEDIMKJHL": [
          180,
          200
        ]
      },
      "PACFFMKGFAO": {
        "OBLDLILOOGO": [
          1,
          2
        ],
        "NKGEDIMKJHL": [
          150,
          200
        ]
      },
      "DJGELAEPLOM": 2,
      "HBJAHCGKJJD": {
        "DOHLNDIPHAJ": "1670"
      },
      "MEGDMLJGGKJ": {
        "DOHLNDIPHAJ": "1668"
      },
      "LMDJKJCPJHF": {
        "DOHLNDIPHAJ": "1671"
      },
      "DNHAGPFHGCE": "Item_Icon_Supply_Dairy_7",
      "LKLEEPGOHLG": 802002,
      "BDPAGGCLONI": 7
    },
    {
      "LGJCPENNFBC": 802003,
      "BKCIGACKEFD": 2,
      "OIJIAGICBCI": [
        5,
        15,
        80
      ],
      "LBBONFCMFAL": [
        3,
        999,
        999
      ],
      "JJFDLLLBOBM": {
        "OBLDLILOOGO": [
          1,
          2
        ],
        "NKGEDIMKJHL": [
          200,
          200
        ]
      },
      "FBELMLMIEED": {
        "OBLDLILOOGO": [
          1,
          2
        ],
        "NKGEDIMKJHL": [
          180,
          200
        ]
      },
      "PACFFMKGFAO": {
        "OBLDLILOOGO": [
          1,
          2
        ],
        "NKGEDIMKJHL": [
          150,
          200
        ]
      },
      "DJGELAEPLOM": 2,
      "HBJAHCGKJJD": {
        "DOHLNDIPHAJ": "1672"
      },
      "MEGDMLJGGKJ": {
        "DOHLNDIPHAJ": "1668"
      },
      "LMDJKJCPJHF": {
        "DOHLNDIPHAJ": "1671"
      },
      "DNHAGPFHGCE": "Item_Icon_Supply_Dairy_8",
      "LKLEEPGOHLG": 802003,
      "BDPAGGCLONI": 7
    },
    {
      "LGJCPENNFBC": 802004,
      "BKCIGACKEFD": 2,
      "OIJIAGICBCI": [
        5,
        15,
        80
      ],
      "LBBONFCMFAL": [
        3,
        999,
        999
      ],
      "JJFDLLLBOBM": {
        "OBLDLILOOGO": [
          1,
          2
        ],
        "NKGEDIMKJHL": [
          200,
          200
        ]
      },
      "FBELMLMIEED": {
        "OBLDLILOOGO": [
          1,
          2
        ],
        "NKGEDIMKJHL": [
          180,
          200
        ]
      },
      "PACFFMKGFAO": {
        "OBLDLILOOGO": [
          1,
          2
        ],
        "NKGEDIMKJHL": [
          150,
          200
        ]
      },
      "DJGELAEPLOM": 2,
      "HBJAHCGKJJD": {
        "DOHLNDIPHAJ": "1673"
      },
      "MEGDMLJGGKJ": {
        "DOHLNDIPHAJ": "1668"
      },
      "LMDJKJCPJHF": {
        "DOHLNDIPHAJ": "1671"
      },
      "DNHAGPFHGCE": "Item_Icon_Supply_Dairy_9",
      "LKLEEPGOHLG": 802004,
      "BDPAGGCLONI": 7
    },
    {
      "LGJCPENNFBC": 802005,
      "BKCIGACKEFD": 2,
      "OIJIAGICBCI": [
        5,
        15,
        80
      ],
      "LBBONFCMFAL": [
        3,
        999,
        999
      ],
      "JJFDLLLBOBM": {
        "OBLDLILOOGO": [
          1,
          2
        ],
        "NKGEDIMKJHL": [
          200,
          200
        ]
      },
      "FBELMLMIEED": {
        "OBLDLILOOGO": [
          1,
          2
        ],
        "NKGEDIMKJHL": [
          180,
          200
        ]
      },
      "PACFFMKGFAO": {
        "OBLDLILOOGO": [
          1,
          2
        ],
        "NKGEDIMKJHL": [
          150,
          200
        ]
      },
      "DJGELAEPLOM": 2,
      "HBJAHCGKJJD": {
        "DOHLNDIPHAJ": "1674"
      },
      "MEGDMLJGGKJ": {
        "DOHLNDIPHAJ": "1668"
      },
      "LMDJKJCPJHF": {
        "DOHLNDIPHAJ": "1671"
      },
      "DNHAGPFHGCE": "Item_Icon_Supply_Dairy_10",
      "LKLEEPGOHLG": 802005,
      "BDPAGGCLONI": 7
    },
    {
      "LGJCPENNFBC": 803001,
      "BKCIGACKEFD": 3,
      "OIJIAGICBCI": [
        5,
        15,
        80
      ],
      "LBBONFCMFAL": [
        3,
        999,
        999
      ],
      "JJFDLLLBOBM": {
        "OBLDLILOOGO": [
          1,
          2
        ],
        "NKGEDIMKJHL": [
          200,
          200
        ]
      },
      "FBELMLMIEED": {
        "OBLDLILOOGO": [
          1,
          2
        ],
        "NKGEDIMKJHL": [
          180,
          200
        ]
      },
      "PACFFMKGFAO": {
        "OBLDLILOOGO": [
          1,
          2
        ],
        "NKGEDIMKJHL": [
          150,
          200
        ]
      },
      "DJGELAEPLOM": 7,
      "HBJAHCGKJJD": {
        "DOHLNDIPHAJ": "1675"
      },
      "MEGDMLJGGKJ": {
        "DOHLNDIPHAJ": "1676"
      },
      "LMDJKJCPJHF": {
        "DOHLNDIPHAJ": "1677"
      },
      "DNHAGPFHGCE": "Item_Icon_Supply_Dairy_11",
      "LKLEEPGOHLG": 803001,
      "BDPAGGCLONI": 21
    },
    {
      "LGJCPENNFBC": 803002,
      "BKCIGACKEFD": 3,
      "OIJIAGICBCI": [
        5,
        15,
        80
      ],
      "LBBONFCMFAL": [
        3,
        999,
        999
      ],
      "JJFDLLLBOBM": {
        "OBLDLILOOGO": [
          1,
          2
        ],
        "NKGEDIMKJHL": [
          200,
          200
        ]
      },
      "FBELMLMIEED": {
        "OBLDLILOOGO": [
          1,
          2
        ],
        "NKGEDIMKJHL": [
          180,
          200
        ]
      },
      "PACFFMKGFAO": {
        "OBLDLILOOGO": [
          1,
          2
        ],
        "NKGEDIMKJHL": [
          150,
          200
        ]
      },
      "DJGELAEPLOM": 7,
      "HBJAHCGKJJD": {
        "DOHLNDIPHAJ": "1678"
      },
      "MEGDMLJGGKJ": {
        "DOHLNDIPHAJ": "1676"
      },
      "LMDJKJCPJHF": {
        "DOHLNDIPHAJ": "1679"
      },
      "DNHAGPFHGCE": "Item_Icon_Supply_Dairy_12",
      "LKLEEPGOHLG": 803002,
      "BDPAGGCLONI": 21
    },
    {
      "LGJCPENNFBC": 803003,
      "BKCIGACKEFD": 3,
      "OIJIAGICBCI": [
        5,
        15,
        80
      ],
      "LBBONFCMFAL": [
        3,
        999,
        999
      ],
      "JJFDLLLBOBM": {
        "OBLDLILOOGO": [
          1,
          2
        ],
        "NKGEDIMKJHL": [
          200,
          200
        ]
      },
      "FBELMLMIEED": {
        "OBLDLILOOGO": [
          1,
          2
        ],
        "NKGEDIMKJHL": [
          180,
          200
        ]
      },
      "PACFFMKGFAO": {
        "OBLDLILOOGO": [
          1,
          2
        ],
        "NKGEDIMKJHL": [
          150,
          200
        ]
      },
      "DJGELAEPLOM": 7,
      "HBJAHCGKJJD": {
        "DOHLNDIPHAJ": "1680"
      },
      "MEGDMLJGGKJ": {
        "DOHLNDIPHAJ": "1676"
      },
      "LMDJKJCPJHF": {
        "DOHLNDIPHAJ": "1681"
      },
      "DNHAGPFHGCE": "Item_Icon_Supply_Dairy_13",
      "LKLEEPGOHLG": 803003,
      "BDPAGGCLONI": 21
    },
    {
      "LGJCPENNFBC": 803004,
      "BKCIGACKEFD": 3,
      "OIJIAGICBCI": [
        5,
        15,
        80
      ],
      "LBBONFCMFAL": [
        3,
        999,
        999
      ],
      "JJFDLLLBOBM": {
        "OBLDLILOOGO": [
          1,
          2
        ],
        "NKGEDIMKJHL": [
          200,
          200
        ]
      },
      "FBELMLMIEED": {
        "OBLDLILOOGO": [
          1,
          2
        ],
        "NKGEDIMKJHL": [
          180,
          200
        ]
      },
      "PACFFMKGFAO": {
        "OBLDLILOOGO": [
          1,
          2
        ],
        "NKGEDIMKJHL": [
          150,
          200
        ]
      },
      "DJGELAEPLOM": 7,
      "HBJAHCGKJJD": {
        "DOHLNDIPHAJ": "1682"
      },
      "MEGDMLJGGKJ": {
        "DOHLNDIPHAJ": "1676"
      },
      "LMDJKJCPJHF": {
        "DOHLNDIPHAJ": "1683"
      },
      "DNHAGPFHGCE": "Item_Icon_Supply_Dairy_14",
      "LKLEEPGOHLG": 803004,
      "BDPAGGCLONI": 21
    },
    {
      "LGJCPENNFBC": 803005,
      "BKCIGACKEFD": 3,
      "OIJIAGICBCI": [
        5,
        15,
        80
      ],
      "LBBONFCMFAL": [
        3,
        999,
        999
      ],
      "JJFDLLLBOBM": {
        "OBLDLILOOGO": [
          1,
          2
        ],
        "NKGEDIMKJHL": [
          200,
          200
        ]
      },
      "FBELMLMIEED": {
        "OBLDLILOOGO": [
          1,
          2
        ],
        "NKGEDIMKJHL": [
          180,
          200
        ]
      },
      "PACFFMKGFAO": {
        "OBLDLILOOGO": [
          1,
          2
        ],
        "NKGEDIMKJHL": [
          150,
          200
        ]
      },
      "DJGELAEPLOM": 7,
      "HBJAHCGKJJD": {
        "DOHLNDIPHAJ": "1684"
      },
      "MEGDMLJGGKJ": {
        "DOHLNDIPHAJ": "1676"
      },
      "LMDJKJCPJHF": {
        "DOHLNDIPHAJ": "1685"
      },
      "DNHAGPFHGCE": "Item_Icon_Supply_Dairy_15",
      "LKLEEPGOHLG": 803005,
      "BDPAGGCLONI": 21
    },
    {
      "LGJCPENNFBC": 804001,
      "BKCIGACKEFD": 4,
      "OIJIAGICBCI": [
        100,
        0,
        0
      ],
      "LBBONFCMFAL": [
        999,
        0,
        0
      ],
      "JJFDLLLBOBM": {
        "OBLDLILOOGO": [
          800001,
          1
        ],
        "NKGEDIMKJHL": [
          6000,
          500
        ]
      },
      "FBELMLMIEED": {
        "OBLDLILOOGO": [
          800001,
          1
        ],
        "NKGEDIMKJHL": [
          4500,
          500
        ]
      },
      "PACFFMKGFAO": {
        "OBLDLILOOGO": [
          800001,
          1
        ],
        "NKGEDIMKJHL": [
          3000,
          500
        ]
      },
      "DJGELAEPLOM": 7,
      "HBJAHCGKJJD": {
        "DOHLNDIPHAJ": "1686"
      },
      "MEGDMLJGGKJ": {
        "DOHLNDIPHAJ": "1687"
      },
      "LMDJKJCPJHF": {
        "DOHLNDIPHAJ": "1688"
      },
      "DNHAGPFHGCE": "Item_Icon_Supply_Dairy_16",
      "LKLEEPGOHLG": 804001,
      "BDPAGGCLONI": 21
    },
    {
      "LGJCPENNFBC": 804002,
      "BKCIGACKEFD": 4,
      "OIJIAGICBCI": [
        100,
        0,
        0
      ],
      "LBBONFCMFAL": [
        999,
        0,
        0
      ],
      "JJFDLLLBOBM": {
        "OBLDLILOOGO": [
          800001,
          1
        ],
        "NKGEDIMKJHL": [
          5000,
          450
        ]
      },
      "FBELMLMIEED": {
        "OBLDLILOOGO": [
          800001,
          1
        ],
        "NKGEDIMKJHL": [
          3750,
          450
        ]
      },
      "PACFFMKGFAO": {
        "OBLDLILOOGO": [
          800001,
          1
        ],
        "NKGEDIMKJHL": [
          2500,
          450
        ]
      },
      "DJGELAEPLOM": 7,
      "HBJAHCGKJJD": {
        "DOHLNDIPHAJ": "1689"
      },
      "MEGDMLJGGKJ": {
        "DOHLNDIPHAJ": "1687"
      },
      "LMDJKJCPJHF": {
        "DOHLNDIPHAJ": "1690"
      },
      "DNHAGPFHGCE": "Item_Icon_Supply_Dairy_17",
      "LKLEEPGOHLG": 804002,
      "BDPAGGCLONI": 21
    },
    {
      "LGJCPENNFBC": 804003,
      "BKCIGACKEFD": 4,
      "OIJIAGICBCI": [
        100,
        0,
        0
      ],
      "LBBONFCMFAL": [
        999,
        0,
        0
      ],
      "JJFDLLLBOBM": {
        "OBLDLILOOGO": [
          800001,
          1
        ],
        "NKGEDIMKJHL": [
          4000,
          400
        ]
      },
      "FBELMLMIEED": {
        "OBLDLILOOGO": [
          800001,
          1
        ],
        "NKGEDIMKJHL": [
          3000,
          400
        ]
      },
      "PACFFMKGFAO": {
        "OBLDLILOOGO": [
          800001,
          1
        ],
        "NKGEDIMKJHL": [
          2000,
          400
        ]
      },
      "DJGELAEPLOM": 7,
      "HBJAHCGKJJD": {
        "DOHLNDIPHAJ": "1691"
      },
      "MEGDMLJGGKJ": {
        "DOHLNDIPHAJ": "1687"
      },
      "LMDJKJCPJHF": {
        "DOHLNDIPHAJ": "1692"
      },
      "DNHAGPFHGCE": "Item_Icon_Supply_Dairy_18",
      "LKLEEPGOHLG": 804003,
      "BDPAGGCLONI": 21
    },
    {
      "LGJCPENNFBC": 804004,
      "BKCIGACKEFD": 4,
      "OIJIAGICBCI": [
        100,
        0,
        0
      ],
      "LBBONFCMFAL": [
        999,
        0,
        0
      ],
      "JJFDLLLBOBM": {
        "OBLDLILOOGO": [
          800001,
          1
        ],
        "NKGEDIMKJHL": [
          3000,
          350
        ]
      },
      "FBELMLMIEED": {
        "OBLDLILOOGO": [
          800001,
          1
        ],
        "NKGEDIMKJHL": [
          2250,
          350
        ]
      },
      "PACFFMKGFAO": {
        "OBLDLILOOGO": [
          800001,
          1
        ],
        "NKGEDIMKJHL": [
          1500,
          350
        ]
      },
      "DJGELAEPLOM": 7,
      "HBJAHCGKJJD": {
        "DOHLNDIPHAJ": "1693"
      },
      "MEGDMLJGGKJ": {
        "DOHLNDIPHAJ": "1687"
      },
      "LMDJKJCPJHF": {
        "DOHLNDIPHAJ": "1694"
      },
      "DNHAGPFHGCE": "Item_Icon_Supply_Dairy_19",
      "LKLEEPGOHLG": 804004,
      "BDPAGGCLONI": 21
    },
    {
      "LGJCPENNFBC": 804005,
      "BKCIGACKEFD": 4,
      "OIJIAGICBCI": [
        100,
        0,
        0
      ],
      "LBBONFCMFAL": [
        999,
        0,
        0
      ],
      "JJFDLLLBOBM": {
        "OBLDLILOOGO": [
          800001,
          1
        ],
        "NKGEDIMKJHL": [
          2000,
          300
        ]
      },
      "FBELMLMIEED": {
        "OBLDLILOOGO": [
          800001,
          1
        ],
        "NKGEDIMKJHL": [
          1500,
          300
        ]
      },
      "PACFFMKGFAO": {
        "OBLDLILOOGO": [
          800001,
          1
        ],
        "NKGEDIMKJHL": [
          1000,
          300
        ]
      },
      "DJGELAEPLOM": 7,
      "HBJAHCGKJJD": {
        "DOHLNDIPHAJ": "1695"
      },
      "MEGDMLJGGKJ": {
        "DOHLNDIPHAJ": "1687"
      },
      "LMDJKJCPJHF": {
        "DOHLNDIPHAJ": "1696"
      },
      "DNHAGPFHGCE": "Item_Icon_Supply_Dairy_20",
      "LKLEEPGOHLG": 804005,
      "BDPAGGCLONI": 21
    }
  ]
}