{
  "data": [
    {
      "LGJCPENNFBC": 3,
      "HBJAHCGKJJD": "闪电",
      "PFNFHACLOGI": 2,
      "FEJBGFFJIKE": 1,
      "CAECOGCHCII": 1,
      "ONEOHDGKMNA": 1,
      "AFOPBBLCOMJ": 3,
      "GOIMBJIIBNC": 2,
      "LBKAFEKMKMC": 1,
      "DCDCLJNABHD": 81101,
      "PDAOCHLDEMP": 300025,
      "NPMGINOGBOF": [
        1004,
        1007,
        1017
      ]
    },
    {
      "LGJCPENNFBC": 7,
      "HBJAHCGKJJD": "佩里缇亚",
      "PFNFHACLOGI": 1,
      "FEJBGFFJIKE": 1,
      "CAECOGCHCII": 1,
      "ONEOHDGKMNA": 1,
      "AFOPBBLCOMJ": 3,
      "GOIMBJIIBNC": 1,
      "LBKAFEKMKMC": 1,
      "DCDCLJNABHD": 81105,
      "PDAOCHLDEMP": 300025,
      "NPMGINOGBOF": [
        1019,
        1014,
        1021
      ]
    }
  ]
}