{
  "data": [
    {
      "LGJCPENNFBC": 10130,
      "HLMJNBDENJL": 101105,
      "HBCFNDOENFL": {
        "DOHLNDIPHAJ": "2130"
      },
      "GKFPJJIHICB": {
        "DOHLNDIPHAJ": "2156"
      },
      "LNEMNKFCAKC": 922,
      "CGFMAIFHLEO": 324,
      "GAGHEBAPHFE": 101,
      "NJHGGAGGPGK": 170049,
      "FBPJHJLDELP": {
        "OBLDLILOOGO": [
          170014
        ],
        "NKGEDIMKJHL": [
          500
        ]
      }
    },
    {
      "LGJCPENNFBC": 10131,
      "HLMJNBDENJL": 101105,
      "HBCFNDOENFL": {
        "DOHLNDIPHAJ": "2132"
      },
      "GKFPJJIHICB": {
        "DOHLNDIPHAJ": "2157"
      },
      "LNEMNKFCAKC": 929,
      "CGFMAIFHLEO": 16,
      "GAGHEBAPHFE": 101,
      "NJHGGAGGPGK": 4,
      "FBPJHJLDELP": {
        "OBLDLILOOGO": [
          170014
        ],
        "NKGEDIMKJHL": [
          500
        ]
      }
    },
    {
      "LGJCPENNFBC": 10132,
      "HLMJNBDENJL": 101106,
      "HBCFNDOENFL": {
        "DOHLNDIPHAJ": "2120"
      },
      "GKFPJJIHICB": {
        "DOHLNDIPHAJ": "2158"
      },
      "LNEMNKFCAKC": 920,
      "CGFMAIFHLEO": 71800,
      "GAGHEBAPHFE": 101,
      "FBPJHJLDELP": {
        "OBLDLILOOGO": [
          170014
        ],
        "NKGEDIMKJHL": [
          500
        ]
      }
    },
    {
      "LGJCPENNFBC": 10133,
      "HLMJNBDENJL": 101106,
      "HBCFNDOENFL": {
        "DOHLNDIPHAJ": "2124"
      },
      "GKFPJJIHICB": {
        "DOHLNDIPHAJ": "2159"
      },
      "LNEMNKFCAKC": 921,
      "CGFMAIFHLEO": 7120,
      "GAGHEBAPHFE": 101,
      "FBPJHJLDELP": {
        "OBLDLILOOGO": [
          170014
        ],
        "NKGEDIMKJHL": [
          500
        ]
      }
    },
    {
      "LGJCPENNFBC": 10134,
      "HLMJNBDENJL": 101106,
      "HBCFNDOENFL": {
        "DOHLNDIPHAJ": "2126"
      },
      "GKFPJJIHICB": {
        "DOHLNDIPHAJ": "2160"
      },
      "LNEMNKFCAKC": 924,
      "CGFMAIFHLEO": 1,
      "GAGHEBAPHFE": 101,
      "NJHGGAGGPGK": 3003,
      "FBPJHJLDELP": {
        "OBLDLILOOGO": [
          170014
        ],
        "NKGEDIMKJHL": [
          800
        ]
      }
    },
    {
      "LGJCPENNFBC": 10135,
      "HLMJNBDENJL": 101106,
      "HBCFNDOENFL": {
        "DOHLNDIPHAJ": "2130"
      },
      "GKFPJJIHICB": {
        "DOHLNDIPHAJ": "2161"
      },
      "LNEMNKFCAKC": 922,
      "CGFMAIFHLEO": 720,
      "GAGHEBAPHFE": 101,
      "NJHGGAGGPGK": 170050,
      "FBPJHJLDELP": {
        "OBLDLILOOGO": [
          170014
        ],
        "NKGEDIMKJHL": [
          500
        ]
      }
    },
    {
      "LGJCPENNFBC": 10136,
      "HLMJNBDENJL": 101106,
      "HBCFNDOENFL": {
        "DOHLNDIPHAJ": "2132"
      },
      "GKFPJJIHICB": {
        "DOHLNDIPHAJ": "2162"
      },
      "LNEMNKFCAKC": 929,
      "CGFMAIFHLEO": 8,
      "GAGHEBAPHFE": 101,
      "NJHGGAGGPGK": 5,
      "FBPJHJLDELP": {
        "OBLDLILOOGO": [
          170014
        ],
        "NKGEDIMKJHL": [
          500
        ]
      }
    },
    {
      "LGJCPENNFBC": 10137,
      "HLMJNBDENJL": 101106,
      "HBCFNDOENFL": {
        "DOHLNDIPHAJ": "2163"
      },
      "GKFPJJIHICB": {
        "DOHLNDIPHAJ": "2164"
      },
      "LNEMNKFCAKC": 575,
      "CGFMAIFHLEO": 1,
      "GAGHEBAPHFE": 4,
      "NJHGGAGGPGK": 6956,
      "FBPJHJLDELP": {
        "OBLDLILOOGO": [
          170014
        ],
        "NKGEDIMKJHL": [
          500
        ]
      }
    },
    {
      "LGJCPENNFBC": 10138,
      "HLMJNBDENJL": 101106,
      "HBCFNDOENFL": {
        "DOHLNDIPHAJ": "2163"
      },
      "GKFPJJIHICB": {
        "DOHLNDIPHAJ": "2165"
      },
      "LNEMNKFCAKC": 575,
      "CGFMAIFHLEO": 1,
      "GAGHEBAPHFE": 4,
      "NJHGGAGGPGK": 6958,
      "FBPJHJLDELP": {
        "OBLDLILOOGO": [
          170014
        ],
        "NKGEDIMKJHL": [
          500
        ]
      }
    },
    {
      "LGJCPENNFBC": 10101,
      "HLMJNBDENJL": 101101,
      "HBCFNDOENFL": {
        "DOHLNDIPHAJ": "2116"
      },
      "GKFPJJIHICB": {
        "DOHLNDIPHAJ": "2117"
      },
      "LNEMNKFCAKC": 402,
      "CGFMAIFHLEO": 21,
      "FBPJHJLDELP": {
        "OBLDLILOOGO": [
          23042
        ],
        "NKGEDIMKJHL": [
          1
        ]
      }
    },
    {
      "LGJCPENNFBC": 10102,
      "HLMJNBDENJL": 101101,
      "HBCFNDOENFL": {
        "DOHLNDIPHAJ": "2120"
      },
      "GKFPJJIHICB": {
        "DOHLNDIPHAJ": "2121"
      },
      "LNEMNKFCAKC": 920,
      "CGFMAIFHLEO": 370,
      "GAGHEBAPHFE": 101,
      "FBPJHJLDELP": {
        "OBLDLILOOGO": [
          170014
        ],
        "NKGEDIMKJHL": [
          500
        ]
      }
    },
    {
      "LGJCPENNFBC": 10103,
      "HLMJNBDENJL": 101101,
      "HBCFNDOENFL": {
        "DOHLNDIPHAJ": "2124"
      },
      "GKFPJJIHICB": {
        "DOHLNDIPHAJ": "2125"
      },
      "LNEMNKFCAKC": 921,
      "CGFMAIFHLEO": 60,
      "GAGHEBAPHFE": 101,
      "FBPJHJLDELP": {
        "OBLDLILOOGO": [
          170014
        ],
        "NKGEDIMKJHL": [
          500
        ]
      }
    },
    {
      "LGJCPENNFBC": 10104,
      "HLMJNBDENJL": 101101,
      "HBCFNDOENFL": {
        "DOHLNDIPHAJ": "2126"
      },
      "GKFPJJIHICB": {
        "DOHLNDIPHAJ": "2127"
      },
      "LNEMNKFCAKC": 924,
      "CGFMAIFHLEO": 1,
      "GAGHEBAPHFE": 101,
      "NJHGGAGGPGK": 1001,
      "FBPJHJLDELP": {
        "OBLDLILOOGO": [
          170014
        ],
        "NKGEDIMKJHL": [
          800
        ]
      }
    },
    {
      "LGJCPENNFBC": 10105,
      "HLMJNBDENJL": 101101,
      "HBCFNDOENFL": {
        "DOHLNDIPHAJ": "2128"
      },
      "GKFPJJIHICB": {
        "DOHLNDIPHAJ": "2129"
      },
      "LNEMNKFCAKC": 5,
      "CGFMAIFHLEO": 60,
      "GAGHEBAPHFE": 170015,
      "FBPJHJLDELP": {
        "OBLDLILOOGO": [
          170014
        ],
        "NKGEDIMKJHL": [
          500
        ]
      }
    },
    {
      "LGJCPENNFBC": 10106,
      "HLMJNBDENJL": 101101,
      "HBCFNDOENFL": {
        "DOHLNDIPHAJ": "2130"
      },
      "GKFPJJIHICB": {
        "DOHLNDIPHAJ": "2131"
      },
      "LNEMNKFCAKC": 922,
      "CGFMAIFHLEO": 60,
      "GAGHEBAPHFE": 101,
      "NJHGGAGGPGK": 170045,
      "FBPJHJLDELP": {
        "OBLDLILOOGO": [
          170014
        ],
        "NKGEDIMKJHL": [
          500
        ]
      }
    },
    {
      "LGJCPENNFBC": 10107,
      "HLMJNBDENJL": 101101,
      "HBCFNDOENFL": {
        "DOHLNDIPHAJ": "2132"
      },
      "GKFPJJIHICB": {
        "DOHLNDIPHAJ": "2133"
      },
      "LNEMNKFCAKC": 929,
      "CGFMAIFHLEO": 3,
      "GAGHEBAPHFE": 101,
      "NJHGGAGGPGK": 2,
      "FBPJHJLDELP": {
        "OBLDLILOOGO": [
          170014
        ],
        "NKGEDIMKJHL": [
          500
        ]
      }
    },
    {
      "LGJCPENNFBC": 10108,
      "HLMJNBDENJL": 101102,
      "HBCFNDOENFL": {
        "DOHLNDIPHAJ": "2120"
      },
      "GKFPJJIHICB": {
        "DOHLNDIPHAJ": "2134"
      },
      "LNEMNKFCAKC": 920,
      "CGFMAIFHLEO": 2130,
      "GAGHEBAPHFE": 101,
      "FBPJHJLDELP": {
        "OBLDLILOOGO": [
          170014
        ],
        "NKGEDIMKJHL": [
          500
        ]
      }
    },
    {
      "LGJCPENNFBC": 10109,
      "HLMJNBDENJL": 101102,
      "HBCFNDOENFL": {
        "DOHLNDIPHAJ": "2124"
      },
      "GKFPJJIHICB": {
        "DOHLNDIPHAJ": "2135"
      },
      "LNEMNKFCAKC": 921,
      "CGFMAIFHLEO": 160,
      "GAGHEBAPHFE": 101,
      "FBPJHJLDELP": {
        "OBLDLILOOGO": [
          170014
        ],
        "NKGEDIMKJHL": [
          500
        ]
      }
    },
    {
      "LGJCPENNFBC": 10110,
      "HLMJNBDENJL": 101102,
      "HBCFNDOENFL": {
        "DOHLNDIPHAJ": "2126"
      },
      "GKFPJJIHICB": {
        "DOHLNDIPHAJ": "2136"
      },
      "LNEMNKFCAKC": 924,
      "CGFMAIFHLEO": 1,
      "GAGHEBAPHFE": 101,
      "NJHGGAGGPGK": 1002,
      "FBPJHJLDELP": {
        "OBLDLILOOGO": [
          170014
        ],
        "NKGEDIMKJHL": [
          800
        ]
      }
    },
    {
      "LGJCPENNFBC": 10111,
      "HLMJNBDENJL": 101102,
      "HBCFNDOENFL": {
        "DOHLNDIPHAJ": "2128"
      },
      "GKFPJJIHICB": {
        "DOHLNDIPHAJ": "2137"
      },
      "LNEMNKFCAKC": 5,
      "CGFMAIFHLEO": 144,
      "GAGHEBAPHFE": 170016,
      "FBPJHJLDELP": {
        "OBLDLILOOGO": [
          170014
        ],
        "NKGEDIMKJHL": [
          500
        ]
      }
    },
    {
      "LGJCPENNFBC": 10112,
      "HLMJNBDENJL": 101102,
      "HBCFNDOENFL": {
        "DOHLNDIPHAJ": "2130"
      },
      "GKFPJJIHICB": {
        "DOHLNDIPHAJ": "2138"
      },
      "LNEMNKFCAKC": 922,
      "CGFMAIFHLEO": 144,
      "GAGHEBAPHFE": 101,
      "NJHGGAGGPGK": 170046,
      "FBPJHJLDELP": {
        "OBLDLILOOGO": [
          170014
        ],
        "NKGEDIMKJHL": [
          500
        ]
      }
    },
    {
      "LGJCPENNFBC": 10113,
      "HLMJNBDENJL": 101102,
      "HBCFNDOENFL": {
        "DOHLNDIPHAJ": "2132"
      },
      "GKFPJJIHICB": {
        "DOHLNDIPHAJ": "2139"
      },
      "LNEMNKFCAKC": 929,
      "CGFMAIFHLEO": 14,
      "GAGHEBAPHFE": 101,
      "NJHGGAGGPGK": 2,
      "FBPJHJLDELP": {
        "OBLDLILOOGO": [
          170014
        ],
        "NKGEDIMKJHL": [
          500
        ]
      }
    },
    {
      "LGJCPENNFBC": 10114,
      "HLMJNBDENJL": 101103,
      "HBCFNDOENFL": {
        "DOHLNDIPHAJ": "2120"
      },
      "GKFPJJIHICB": {
        "DOHLNDIPHAJ": "2140"
      },
      "LNEMNKFCAKC": 920,
      "CGFMAIFHLEO": 5800,
      "GAGHEBAPHFE": 101,
      "FBPJHJLDELP": {
        "OBLDLILOOGO": [
          170014
        ],
        "NKGEDIMKJHL": [
          500
        ]
      }
    },
    {
      "LGJCPENNFBC": 10115,
      "HLMJNBDENJL": 101103,
      "HBCFNDOENFL": {
        "DOHLNDIPHAJ": "2124"
      },
      "GKFPJJIHICB": {
        "DOHLNDIPHAJ": "2141"
      },
      "LNEMNKFCAKC": 921,
      "CGFMAIFHLEO": 700,
      "GAGHEBAPHFE": 101,
      "FBPJHJLDELP": {
        "OBLDLILOOGO": [
          170014
        ],
        "NKGEDIMKJHL": [
          500
        ]
      }
    },
    {
      "LGJCPENNFBC": 10116,
      "HLMJNBDENJL": 101103,
      "HBCFNDOENFL": {
        "DOHLNDIPHAJ": "2126"
      },
      "GKFPJJIHICB": {
        "DOHLNDIPHAJ": "2142"
      },
      "LNEMNKFCAKC": 924,
      "CGFMAIFHLEO": 1,
      "GAGHEBAPHFE": 101,
      "NJHGGAGGPGK": 2001,
      "FBPJHJLDELP": {
        "OBLDLILOOGO": [
          170014
        ],
        "NKGEDIMKJHL": [
          800
        ]
      }
    },
    {
      "LGJCPENNFBC": 10117,
      "HLMJNBDENJL": 101103,
      "HBCFNDOENFL": {
        "DOHLNDIPHAJ": "2128"
      },
      "GKFPJJIHICB": {
        "DOHLNDIPHAJ": "2143"
      },
      "LNEMNKFCAKC": 5,
      "CGFMAIFHLEO": 252,
      "GAGHEBAPHFE": 170017,
      "FBPJHJLDELP": {
        "OBLDLILOOGO": [
          170014
        ],
        "NKGEDIMKJHL": [
          500
        ]
      }
    },
    {
      "LGJCPENNFBC": 10118,
      "HLMJNBDENJL": 101103,
      "HBCFNDOENFL": {
        "DOHLNDIPHAJ": "2130"
      },
      "GKFPJJIHICB": {
        "DOHLNDIPHAJ": "2144"
      },
      "LNEMNKFCAKC": 922,
      "CGFMAIFHLEO": 252,
      "GAGHEBAPHFE": 101,
      "NJHGGAGGPGK": 170047,
      "FBPJHJLDELP": {
        "OBLDLILOOGO": [
          170014
        ],
        "NKGEDIMKJHL": [
          500
        ]
      }
    },
    {
      "LGJCPENNFBC": 10119,
      "HLMJNBDENJL": 101103,
      "HBCFNDOENFL": {
        "DOHLNDIPHAJ": "2132"
      },
      "GKFPJJIHICB": {
        "DOHLNDIPHAJ": "2145"
      },
      "LNEMNKFCAKC": 929,
      "CGFMAIFHLEO": 14,
      "GAGHEBAPHFE": 101,
      "NJHGGAGGPGK": 3,
      "FBPJHJLDELP": {
        "OBLDLILOOGO": [
          170014
        ],
        "NKGEDIMKJHL": [
          500
        ]
      }
    },
    {
      "LGJCPENNFBC": 10120,
      "HLMJNBDENJL": 101104,
      "HBCFNDOENFL": {
        "DOHLNDIPHAJ": "2120"
      },
      "GKFPJJIHICB": {
        "DOHLNDIPHAJ": "2146"
      },
      "LNEMNKFCAKC": 920,
      "CGFMAIFHLEO": 12300,
      "GAGHEBAPHFE": 101,
      "FBPJHJLDELP": {
        "OBLDLILOOGO": [
          170014
        ],
        "NKGEDIMKJHL": [
          500
        ]
      }
    },
    {
      "LGJCPENNFBC": 10121,
      "HLMJNBDENJL": 101104,
      "HBCFNDOENFL": {
        "DOHLNDIPHAJ": "2124"
      },
      "GKFPJJIHICB": {
        "DOHLNDIPHAJ": "2147"
      },
      "LNEMNKFCAKC": 921,
      "CGFMAIFHLEO": 1300,
      "GAGHEBAPHFE": 101,
      "FBPJHJLDELP": {
        "OBLDLILOOGO": [
          170014
        ],
        "NKGEDIMKJHL": [
          500
        ]
      }
    },
    {
      "LGJCPENNFBC": 10122,
      "HLMJNBDENJL": 101104,
      "HBCFNDOENFL": {
        "DOHLNDIPHAJ": "2126"
      },
      "GKFPJJIHICB": {
        "DOHLNDIPHAJ": "2148"
      },
      "LNEMNKFCAKC": 924,
      "CGFMAIFHLEO": 1,
      "GAGHEBAPHFE": 101,
      "NJHGGAGGPGK": 2003,
      "FBPJHJLDELP": {
        "OBLDLILOOGO": [
          170014
        ],
        "NKGEDIMKJHL": [
          800
        ]
      }
    },
    {
      "LGJCPENNFBC": 10123,
      "HLMJNBDENJL": 101104,
      "HBCFNDOENFL": {
        "DOHLNDIPHAJ": "2128"
      },
      "GKFPJJIHICB": {
        "DOHLNDIPHAJ": "2149"
      },
      "LNEMNKFCAKC": 5,
      "CGFMAIFHLEO": 288,
      "GAGHEBAPHFE": 170018,
      "FBPJHJLDELP": {
        "OBLDLILOOGO": [
          170014
        ],
        "NKGEDIMKJHL": [
          500
        ]
      }
    },
    {
      "LGJCPENNFBC": 10124,
      "HLMJNBDENJL": 101104,
      "HBCFNDOENFL": {
        "DOHLNDIPHAJ": "2130"
      },
      "GKFPJJIHICB": {
        "DOHLNDIPHAJ": "2150"
      },
      "LNEMNKFCAKC": 922,
      "CGFMAIFHLEO": 288,
      "GAGHEBAPHFE": 101,
      "NJHGGAGGPGK": 170048,
      "FBPJHJLDELP": {
        "OBLDLILOOGO": [
          170014
        ],
        "NKGEDIMKJHL": [
          500
        ]
      }
    },
    {
      "LGJCPENNFBC": 10125,
      "HLMJNBDENJL": 101104,
      "HBCFNDOENFL": {
        "DOHLNDIPHAJ": "2132"
      },
      "GKFPJJIHICB": {
        "DOHLNDIPHAJ": "2151"
      },
      "LNEMNKFCAKC": 929,
      "CGFMAIFHLEO": 24,
      "GAGHEBAPHFE": 101,
      "NJHGGAGGPGK": 3,
      "FBPJHJLDELP": {
        "OBLDLILOOGO": [
          170014
        ],
        "NKGEDIMKJHL": [
          500
        ]
      }
    },
    {
      "LGJCPENNFBC": 10126,
      "HLMJNBDENJL": 101105,
      "HBCFNDOENFL": {
        "DOHLNDIPHAJ": "2120"
      },
      "GKFPJJIHICB": {
        "DOHLNDIPHAJ": "2152"
      },
      "LNEMNKFCAKC": 920,
      "CGFMAIFHLEO": 34300,
      "GAGHEBAPHFE": 101,
      "FBPJHJLDELP": {
        "OBLDLILOOGO": [
          170014
        ],
        "NKGEDIMKJHL": [
          500
        ]
      }
    },
    {
      "LGJCPENNFBC": 10127,
      "HLMJNBDENJL": 101105,
      "HBCFNDOENFL": {
        "DOHLNDIPHAJ": "2124"
      },
      "GKFPJJIHICB": {
        "DOHLNDIPHAJ": "2153"
      },
      "LNEMNKFCAKC": 921,
      "CGFMAIFHLEO": 3580,
      "GAGHEBAPHFE": 101,
      "FBPJHJLDELP": {
        "OBLDLILOOGO": [
          170014
        ],
        "NKGEDIMKJHL": [
          500
        ]
      }
    },
    {
      "LGJCPENNFBC": 10128,
      "HLMJNBDENJL": 101105,
      "HBCFNDOENFL": {
        "DOHLNDIPHAJ": "2126"
      },
      "GKFPJJIHICB": {
        "DOHLNDIPHAJ": "2154"
      },
      "LNEMNKFCAKC": 924,
      "CGFMAIFHLEO": 1,
      "GAGHEBAPHFE": 101,
      "NJHGGAGGPGK": 3001,
      "FBPJHJLDELP": {
        "OBLDLILOOGO": [
          170014
        ],
        "NKGEDIMKJHL": [
          800
        ]
      }
    },
    {
      "LGJCPENNFBC": 10129,
      "HLMJNBDENJL": 101105,
      "HBCFNDOENFL": {
        "DOHLNDIPHAJ": "2128"
      },
      "GKFPJJIHICB": {
        "DOHLNDIPHAJ": "2155"
      },
      "LNEMNKFCAKC": 5,
      "CGFMAIFHLEO": 324,
      "GAGHEBAPHFE": 170019,
      "FBPJHJLDELP": {
        "OBLDLILOOGO": [
          170014
        ],
        "NKGEDIMKJHL": [
          500
        ]
      }
    }
  ]
}