{
  "data": [
    {
      "LGJCPENNFBC": 510,
      "OBDBAJHHNDI": 510,
      "OIGJHKMMBLD": 2,
      "PEFDOIHIIBG": 1,
      "BFBNEHIIGKB": [
        1,
        4,
        3
      ],
      "HBNHAKJHDJC": 13,
      "DBLDBAJDLBP": 8,
      "EOCOOJDFMLJ": 6
    },
    {
      "LGJCPENNFBC": 511,
      "OBDBAJHHNDI": 511,
      "OIGJHKMMBLD": 2,
      "PEFDOIHIIBG": 1,
      "BFBNEHIIGKB": [
        1,
        2,
        3
      ],
      "HBNHAKJHDJC": 6,
      "DBLDBAJDLBP": 9,
      "EOCOOJDFMLJ": 7
    },
    {
      "LGJCPENNFBC": 512,
      "OBDBAJHHNDI": 512,
      "OIGJHKMMBLD": 2,
      "PEFDOIHIIBG": 1,
      "BFBNEHIIGKB": [
        1,
        5,
        6
      ],
      "HBNHAKJHDJC": 4,
      "DBLDBAJDLBP": 9,
      "EOCOOJDFMLJ": 7
    },
    {
      "LGJCPENNFBC": 513,
      "OBDBAJHHNDI": 513,
      "OIGJHKMMBLD": 2,
      "PEFDOIHIIBG": 1,
      "BFBNEHIIGKB": [
        1,
        4,
        3
      ],
      "HBNHAKJHDJC": 2,
      "DBLDBAJDLBP": 9,
      "EOCOOJDFMLJ": 7
    },
    {
      "LGJCPENNFBC": 514,
      "OBDBAJHHNDI": 514,
      "OIGJHKMMBLD": 2,
      "PEFDOIHIIBG": 1,
      "BFBNEHIIGKB": [
        1,
        5,
        6
      ],
      "HBNHAKJHDJC": 6,
      "DBLDBAJDLBP": 9,
      "EOCOOJDFMLJ": 7
    },
    {
      "LGJCPENNFBC": 515,
      "OBDBAJHHNDI": 515,
      "OIGJHKMMBLD": 2,
      "PEFDOIHIIBG": 1,
      "BFBNEHIIGKB": [
        1,
        4,
        3
      ],
      "HBNHAKJHDJC": 10,
      "DBLDBAJDLBP": 9,
      "EOCOOJDFMLJ": 7
    },
    {
      "LGJCPENNFBC": 810,
      "OBDBAJHHNDI": 810,
      "OIGJHKMMBLD": 2,
      "PEFDOIHIIBG": 1,
      "BFBNEHIIGKB": [
        1,
        4,
        3
      ],
      "HBNHAKJHDJC": 4,
      "DBLDBAJDLBP": 8,
      "EOCOOJDFMLJ": 6
    },
    {
      "LGJCPENNFBC": 811,
      "OBDBAJHHNDI": 811,
      "OIGJHKMMBLD": 2,
      "PEFDOIHIIBG": 1,
      "BFBNEHIIGKB": [
        1,
        2,
        3
      ],
      "HBNHAKJHDJC": 6,
      "DBLDBAJDLBP": 9,
      "EOCOOJDFMLJ": 7
    },
    {
      "LGJCPENNFBC": 812,
      "OBDBAJHHNDI": 812,
      "OIGJHKMMBLD": 2,
      "PEFDOIHIIBG": 1,
      "BFBNEHIIGKB": [
        1,
        5,
        6
      ],
      "HBNHAKJHDJC": 8,
      "DBLDBAJDLBP": 9,
      "EOCOOJDFMLJ": 7
    },
    {
      "LGJCPENNFBC": 813,
      "OBDBAJHHNDI": 813,
      "OIGJHKMMBLD": 2,
      "PEFDOIHIIBG": 1,
      "BFBNEHIIGKB": [
        1,
        4,
        3
      ],
      "HBNHAKJHDJC": 1,
      "DBLDBAJDLBP": 9,
      "EOCOOJDFMLJ": 7
    },
    {
      "LGJCPENNFBC": 814,
      "OBDBAJHHNDI": 814,
      "OIGJHKMMBLD": 2,
      "PEFDOIHIIBG": 1,
      "BFBNEHIIGKB": [
        1,
        5,
        6
      ],
      "HBNHAKJHDJC": 2,
      "DBLDBAJDLBP": 9,
      "EOCOOJDFMLJ": 7
    },
    {
      "LGJCPENNFBC": 815,
      "OBDBAJHHNDI": 815,
      "OIGJHKMMBLD": 2,
      "PEFDOIHIIBG": 1,
      "BFBNEHIIGKB": [
        1,
        4,
        3
      ],
      "HBNHAKJHDJC": 5,
      "DBLDBAJDLBP": 9,
      "EOCOOJDFMLJ": 7
    },
    {
      "LGJCPENNFBC": 816,
      "OBDBAJHHNDI": 816,
      "OIGJHKMMBLD": 1,
      "PEFDOIHIIBG": 1,
      "BFBNEHIIGKB": [
        1,
        2,
        3
      ],
      "HBNHAKJHDJC": 4,
      "DBLDBAJDLBP": 7,
      "EOCOOJDFMLJ": 5
    },
    {
      "LGJCPENNFBC": 817,
      "OBDBAJHHNDI": 817,
      "OIGJHKMMBLD": 1,
      "PEFDOIHIIBG": 1,
      "BFBNEHIIGKB": [
        1,
        5,
        6
      ],
      "HBNHAKJHDJC": 6,
      "DBLDBAJDLBP": 7,
      "EOCOOJDFMLJ": 5
    },
    {
      "LGJCPENNFBC": 818,
      "OBDBAJHHNDI": 818,
      "OIGJHKMMBLD": 3,
      "PEFDOIHIIBG": 2,
      "BFBNEHIIGKB": [
        1,
        4,
        3
      ],
      "HBNHAKJHDJC": 9,
      "DBLDBAJDLBP": 7,
      "EOCOOJDFMLJ": 5
    },
    {
      "LGJCPENNFBC": 819,
      "OBDBAJHHNDI": 819,
      "OIGJHKMMBLD": 3,
      "PEFDOIHIIBG": 2,
      "BFBNEHIIGKB": [
        1,
        5,
        6
      ],
      "HBNHAKJHDJC": 1,
      "DBLDBAJDLBP": 7,
      "EOCOOJDFMLJ": 5
    },
    {
      "LGJCPENNFBC": 820,
      "OBDBAJHHNDI": 820,
      "OIGJHKMMBLD": 3,
      "PEFDOIHIIBG": 2,
      "BFBNEHIIGKB": [
        1,
        4,
        3
      ],
      "HBNHAKJHDJC": 2,
      "DBLDBAJDLBP": 7,
      "EOCOOJDFMLJ": 5
    },
    {
      "LGJCPENNFBC": 821,
      "OBDBAJHHNDI": 821,
      "OIGJHKMMBLD": 3,
      "PEFDOIHIIBG": 2,
      "BFBNEHIIGKB": [
        1,
        2,
        3
      ],
      "HBNHAKJHDJC": 5,
      "DBLDBAJDLBP": 8,
      "EOCOOJDFMLJ": 6
    },
    {
      "LGJCPENNFBC": 822,
      "OBDBAJHHNDI": 822,
      "OIGJHKMMBLD": 3,
      "PEFDOIHIIBG": 2,
      "BFBNEHIIGKB": [
        1,
        5,
        6
      ],
      "HBNHAKJHDJC": 4,
      "DBLDBAJDLBP": 8,
      "EOCOOJDFMLJ": 6
    },
    {
      "LGJCPENNFBC": 823,
      "OBDBAJHHNDI": 823,
      "OIGJHKMMBLD": 2,
      "PEFDOIHIIBG": 1,
      "BFBNEHIIGKB": [
        1,
        4,
        3
      ],
      "HBNHAKJHDJC": 6,
      "DBLDBAJDLBP": 8,
      "EOCOOJDFMLJ": 6
    },
    {
      "LGJCPENNFBC": 824,
      "OBDBAJHHNDI": 824,
      "OIGJHKMMBLD": 2,
      "PEFDOIHIIBG": 1,
      "BFBNEHIIGKB": [
        1,
        5,
        6
      ],
      "HBNHAKJHDJC": 10,
      "DBLDBAJDLBP": 8,
      "EOCOOJDFMLJ": 6
    },
    {
      "LGJCPENNFBC": 825,
      "OBDBAJHHNDI": 825,
      "OIGJHKMMBLD": 2,
      "PEFDOIHIIBG": 1,
      "BFBNEHIIGKB": [
        1,
        4,
        3
      ],
      "HBNHAKJHDJC": 1,
      "DBLDBAJDLBP": 8,
      "EOCOOJDFMLJ": 6
    },
    {
      "LGJCPENNFBC": 826,
      "OBDBAJHHNDI": 826,
      "OIGJHKMMBLD": 2,
      "PEFDOIHIIBG": 1,
      "BFBNEHIIGKB": [
        1,
        2,
        3
      ],
      "HBNHAKJHDJC": 2,
      "DBLDBAJDLBP": 9,
      "EOCOOJDFMLJ": 7
    },
    {
      "LGJCPENNFBC": 827,
      "OBDBAJHHNDI": 827,
      "OIGJHKMMBLD": 2,
      "PEFDOIHIIBG": 1,
      "BFBNEHIIGKB": [
        1,
        5,
        6
      ],
      "HBNHAKJHDJC": 5,
      "DBLDBAJDLBP": 9,
      "EOCOOJDFMLJ": 7
    },
    {
      "LGJCPENNFBC": 828,
      "OBDBAJHHNDI": 828,
      "OIGJHKMMBLD": 2,
      "PEFDOIHIIBG": 1,
      "BFBNEHIIGKB": [
        1,
        4,
        3
      ],
      "HBNHAKJHDJC": 4,
      "DBLDBAJDLBP": 9,
      "EOCOOJDFMLJ": 7
    },
    {
      "LGJCPENNFBC": 829,
      "OBDBAJHHNDI": 829,
      "OIGJHKMMBLD": 2,
      "PEFDOIHIIBG": 1,
      "BFBNEHIIGKB": [
        1,
        5,
        6
      ],
      "HBNHAKJHDJC": 6,
      "DBLDBAJDLBP": 9,
      "EOCOOJDFMLJ": 7
    },
    {
      "LGJCPENNFBC": 110,
      "OBDBAJHHNDI": 110,
      "OIGJHKMMBLD": 2,
      "PEFDOIHIIBG": 1,
      "BFBNEHIIGKB": [
        2,
        3
      ],
      "HBNHAKJHDJC": 3,
      "DBLDBAJDLBP": 8,
      "EOCOOJDFMLJ": 6
    },
    {
      "LGJCPENNFBC": 111,
      "OBDBAJHHNDI": 111,
      "OIGJHKMMBLD": 2,
      "PEFDOIHIIBG": 1,
      "BFBNEHIIGKB": [
        1,
        3
      ],
      "HBNHAKJHDJC": 1,
      "DBLDBAJDLBP": 8,
      "EOCOOJDFMLJ": 6
    },
    {
      "LGJCPENNFBC": 112,
      "OBDBAJHHNDI": 112,
      "OIGJHKMMBLD": 2,
      "PEFDOIHIIBG": 1,
      "BFBNEHIIGKB": [
        2,
        3
      ],
      "HBNHAKJHDJC": 2,
      "DBLDBAJDLBP": 8,
      "EOCOOJDFMLJ": 6
    },
    {
      "LGJCPENNFBC": 113,
      "OBDBAJHHNDI": 113,
      "OIGJHKMMBLD": 2,
      "PEFDOIHIIBG": 1,
      "BFBNEHIIGKB": [
        1,
        3
      ],
      "HBNHAKJHDJC": 1,
      "DBLDBAJDLBP": 8,
      "EOCOOJDFMLJ": 6
    },
    {
      "LGJCPENNFBC": 114,
      "OBDBAJHHNDI": 114,
      "OIGJHKMMBLD": 2,
      "PEFDOIHIIBG": 1,
      "BFBNEHIIGKB": [
        2,
        3
      ],
      "HBNHAKJHDJC": 3,
      "DBLDBAJDLBP": 8,
      "EOCOOJDFMLJ": 6
    },
    {
      "LGJCPENNFBC": 115,
      "OBDBAJHHNDI": 115,
      "OIGJHKMMBLD": 2,
      "PEFDOIHIIBG": 1,
      "BFBNEHIIGKB": [
        1,
        2,
        3
      ],
      "HBNHAKJHDJC": 1,
      "DBLDBAJDLBP": 8,
      "EOCOOJDFMLJ": 6
    },
    {
      "LGJCPENNFBC": 210,
      "OBDBAJHHNDI": 210,
      "OIGJHKMMBLD": 2,
      "PEFDOIHIIBG": 1,
      "BFBNEHIIGKB": [
        1,
        2,
        3,
        4
      ],
      "HBNHAKJHDJC": 7,
      "DBLDBAJDLBP": 8,
      "EOCOOJDFMLJ": 6
    },
    {
      "LGJCPENNFBC": 211,
      "OBDBAJHHNDI": 211,
      "OIGJHKMMBLD": 2,
      "PEFDOIHIIBG": 1,
      "BFBNEHIIGKB": [
        1,
        2,
        3,
        4
      ],
      "HBNHAKJHDJC": 4,
      "DBLDBAJDLBP": 8,
      "EOCOOJDFMLJ": 6
    },
    {
      "LGJCPENNFBC": 212,
      "OBDBAJHHNDI": 212,
      "OIGJHKMMBLD": 2,
      "PEFDOIHIIBG": 1,
      "BFBNEHIIGKB": [
        1,
        2,
        3,
        4
      ],
      "HBNHAKJHDJC": 4,
      "DBLDBAJDLBP": 8,
      "EOCOOJDFMLJ": 6
    },
    {
      "LGJCPENNFBC": 213,
      "OBDBAJHHNDI": 213,
      "OIGJHKMMBLD": 2,
      "PEFDOIHIIBG": 1,
      "BFBNEHIIGKB": [
        1,
        2,
        3,
        4
      ],
      "HBNHAKJHDJC": 4,
      "DBLDBAJDLBP": 8,
      "EOCOOJDFMLJ": 6
    },
    {
      "LGJCPENNFBC": 214,
      "OBDBAJHHNDI": 214,
      "OIGJHKMMBLD": 2,
      "PEFDOIHIIBG": 1,
      "BFBNEHIIGKB": [
        1,
        2,
        3,
        4
      ],
      "HBNHAKJHDJC": 4,
      "DBLDBAJDLBP": 8,
      "EOCOOJDFMLJ": 6
    },
    {
      "LGJCPENNFBC": 215,
      "OBDBAJHHNDI": 215,
      "OIGJHKMMBLD": 2,
      "PEFDOIHIIBG": 1,
      "BFBNEHIIGKB": [
        1,
        2,
        3,
        4
      ],
      "HBNHAKJHDJC": 7,
      "DBLDBAJDLBP": 8,
      "EOCOOJDFMLJ": 6
    },
    {
      "LGJCPENNFBC": 301,
      "OBDBAJHHNDI": 301,
      "OIGJHKMMBLD": 1,
      "PEFDOIHIIBG": 1,
      "BFBNEHIIGKB": [
        1,
        3
      ],
      "HBNHAKJHDJC": 2,
      "DBLDBAJDLBP": 7,
      "EOCOOJDFMLJ": 5
    },
    {
      "LGJCPENNFBC": 302,
      "OBDBAJHHNDI": 302,
      "OIGJHKMMBLD": 1,
      "PEFDOIHIIBG": 1,
      "BFBNEHIIGKB": [
        2,
        5,
        3
      ],
      "HBNHAKJHDJC": 4,
      "DBLDBAJDLBP": 7,
      "EOCOOJDFMLJ": 5
    },
    {
      "LGJCPENNFBC": 303,
      "OBDBAJHHNDI": 303,
      "OIGJHKMMBLD": 1,
      "PEFDOIHIIBG": 1,
      "BFBNEHIIGKB": [
        1,
        5,
        4
      ],
      "HBNHAKJHDJC": 5,
      "DBLDBAJDLBP": 7,
      "EOCOOJDFMLJ": 5
    },
    {
      "LGJCPENNFBC": 304,
      "OBDBAJHHNDI": 304,
      "OIGJHKMMBLD": 3,
      "PEFDOIHIIBG": 2,
      "BFBNEHIIGKB": [
        1,
        3,
        5
      ],
      "HBNHAKJHDJC": 601,
      "DBLDBAJDLBP": 7,
      "EOCOOJDFMLJ": 5
    },
    {
      "LGJCPENNFBC": 305,
      "OBDBAJHHNDI": 305,
      "OIGJHKMMBLD": 3,
      "PEFDOIHIIBG": 2,
      "BFBNEHIIGKB": [
        2,
        4,
        5
      ],
      "HBNHAKJHDJC": 4,
      "DBLDBAJDLBP": 7,
      "EOCOOJDFMLJ": 5
    },
    {
      "LGJCPENNFBC": 306,
      "OBDBAJHHNDI": 306,
      "OIGJHKMMBLD": 3,
      "PEFDOIHIIBG": 2,
      "BFBNEHIIGKB": [
        1,
        3
      ],
      "HBNHAKJHDJC": 8,
      "DBLDBAJDLBP": 8,
      "EOCOOJDFMLJ": 6
    },
    {
      "LGJCPENNFBC": 307,
      "OBDBAJHHNDI": 307,
      "OIGJHKMMBLD": 3,
      "PEFDOIHIIBG": 2,
      "BFBNEHIIGKB": [
        2,
        5,
        3
      ],
      "HBNHAKJHDJC": 7,
      "DBLDBAJDLBP": 8,
      "EOCOOJDFMLJ": 6
    },
    {
      "LGJCPENNFBC": 308,
      "OBDBAJHHNDI": 308,
      "OIGJHKMMBLD": 2,
      "PEFDOIHIIBG": 1,
      "BFBNEHIIGKB": [
        1,
        5,
        4
      ],
      "HBNHAKJHDJC": 4,
      "DBLDBAJDLBP": 8,
      "EOCOOJDFMLJ": 6
    },
    {
      "LGJCPENNFBC": 309,
      "OBDBAJHHNDI": 309,
      "OIGJHKMMBLD": 2,
      "PEFDOIHIIBG": 1,
      "BFBNEHIIGKB": [
        1,
        3,
        6
      ],
      "HBNHAKJHDJC": 2,
      "DBLDBAJDLBP": 8,
      "EOCOOJDFMLJ": 6
    },
    {
      "LGJCPENNFBC": 601,
      "OBDBAJHHNDI": 601,
      "OIGJHKMMBLD": 1,
      "PEFDOIHIIBG": 1,
      "BFBNEHIIGKB": [
        1,
        2,
        3
      ],
      "HBNHAKJHDJC": 4,
      "DBLDBAJDLBP": 7,
      "EOCOOJDFMLJ": 5
    },
    {
      "LGJCPENNFBC": 602,
      "OBDBAJHHNDI": 602,
      "OIGJHKMMBLD": 1,
      "PEFDOIHIIBG": 1,
      "BFBNEHIIGKB": [
        1,
        4,
        5
      ],
      "HBNHAKJHDJC": 6,
      "DBLDBAJDLBP": 7,
      "EOCOOJDFMLJ": 5
    },
    {
      "LGJCPENNFBC": 603,
      "OBDBAJHHNDI": 603,
      "OIGJHKMMBLD": 1,
      "PEFDOIHIIBG": 1,
      "BFBNEHIIGKB": [
        1,
        2,
        6
      ],
      "HBNHAKJHDJC": 7,
      "DBLDBAJDLBP": 7,
      "EOCOOJDFMLJ": 5
    },
    {
      "LGJCPENNFBC": 604,
      "OBDBAJHHNDI": 604,
      "OIGJHKMMBLD": 3,
      "PEFDOIHIIBG": 2,
      "BFBNEHIIGKB": [
        1,
        5,
        6
      ],
      "HBNHAKJHDJC": 4,
      "DBLDBAJDLBP": 7,
      "EOCOOJDFMLJ": 5
    },
    {
      "LGJCPENNFBC": 605,
      "OBDBAJHHNDI": 605,
      "OIGJHKMMBLD": 3,
      "PEFDOIHIIBG": 2,
      "BFBNEHIIGKB": [
        1,
        4,
        3
      ],
      "HBNHAKJHDJC": 6,
      "DBLDBAJDLBP": 7,
      "EOCOOJDFMLJ": 5
    },
    {
      "LGJCPENNFBC": 606,
      "OBDBAJHHNDI": 606,
      "OIGJHKMMBLD": 3,
      "PEFDOIHIIBG": 2,
      "BFBNEHIIGKB": [
        1,
        2,
        3
      ],
      "HBNHAKJHDJC": 13,
      "DBLDBAJDLBP": 8,
      "EOCOOJDFMLJ": 6
    },
    {
      "LGJCPENNFBC": 607,
      "OBDBAJHHNDI": 607,
      "OIGJHKMMBLD": 3,
      "PEFDOIHIIBG": 2,
      "BFBNEHIIGKB": [
        1,
        5,
        6
      ],
      "HBNHAKJHDJC": 12,
      "DBLDBAJDLBP": 8,
      "EOCOOJDFMLJ": 6
    },
    {
      "LGJCPENNFBC": 608,
      "OBDBAJHHNDI": 608,
      "OIGJHKMMBLD": 2,
      "PEFDOIHIIBG": 1,
      "BFBNEHIIGKB": [
        1,
        4,
        3
      ],
      "HBNHAKJHDJC": 2,
      "DBLDBAJDLBP": 8,
      "EOCOOJDFMLJ": 6
    },
    {
      "LGJCPENNFBC": 609,
      "OBDBAJHHNDI": 609,
      "OIGJHKMMBLD": 2,
      "PEFDOIHIIBG": 1,
      "BFBNEHIIGKB": [
        1,
        5,
        6
      ],
      "HBNHAKJHDJC": 6,
      "DBLDBAJDLBP": 8,
      "EOCOOJDFMLJ": 6
    },
    {
      "LGJCPENNFBC": 710,
      "OBDBAJHHNDI": 710,
      "OIGJHKMMBLD": 2,
      "PEFDOIHIIBG": 1,
      "BFBNEHIIGKB": [
        1,
        4,
        3
      ],
      "HBNHAKJHDJC": 13,
      "DBLDBAJDLBP": 8,
      "EOCOOJDFMLJ": 6
    },
    {
      "LGJCPENNFBC": 711,
      "OBDBAJHHNDI": 711,
      "OIGJHKMMBLD": 2,
      "PEFDOIHIIBG": 1,
      "BFBNEHIIGKB": [
        1,
        2,
        3
      ],
      "HBNHAKJHDJC": 2,
      "DBLDBAJDLBP": 9,
      "EOCOOJDFMLJ": 7
    },
    {
      "LGJCPENNFBC": 712,
      "OBDBAJHHNDI": 712,
      "OIGJHKMMBLD": 2,
      "PEFDOIHIIBG": 1,
      "BFBNEHIIGKB": [
        1,
        5,
        6
      ],
      "HBNHAKJHDJC": 6,
      "DBLDBAJDLBP": 9,
      "EOCOOJDFMLJ": 7
    },
    {
      "LGJCPENNFBC": 713,
      "OBDBAJHHNDI": 713,
      "OIGJHKMMBLD": 2,
      "PEFDOIHIIBG": 1,
      "BFBNEHIIGKB": [
        1,
        4,
        3
      ],
      "HBNHAKJHDJC": 4,
      "DBLDBAJDLBP": 9,
      "EOCOOJDFMLJ": 7
    },
    {
      "LGJCPENNFBC": 714,
      "OBDBAJHHNDI": 714,
      "OIGJHKMMBLD": 2,
      "PEFDOIHIIBG": 1,
      "BFBNEHIIGKB": [
        1,
        5,
        6
      ],
      "HBNHAKJHDJC": 2,
      "DBLDBAJDLBP": 9,
      "EOCOOJDFMLJ": 7
    },
    {
      "LGJCPENNFBC": 715,
      "OBDBAJHHNDI": 715,
      "OIGJHKMMBLD": 2,
      "PEFDOIHIIBG": 1,
      "BFBNEHIIGKB": [
        1,
        4,
        3
      ],
      "HBNHAKJHDJC": 13,
      "DBLDBAJDLBP": 9,
      "EOCOOJDFMLJ": 7
    },
    {
      "LGJCPENNFBC": 801,
      "OBDBAJHHNDI": 801,
      "OIGJHKMMBLD": 1,
      "PEFDOIHIIBG": 5,
      "BFBNEHIIGKB": [
        1,
        2,
        3
      ],
      "HBNHAKJHDJC": 1,
      "DBLDBAJDLBP": 50,
      "EOCOOJDFMLJ": 20
    },
    {
      "LGJCPENNFBC": 802,
      "OBDBAJHHNDI": 802,
      "OIGJHKMMBLD": 1,
      "PEFDOIHIIBG": 1,
      "BFBNEHIIGKB": [
        1,
        5,
        6
      ],
      "HBNHAKJHDJC": 2,
      "DBLDBAJDLBP": 7,
      "EOCOOJDFMLJ": 5
    },
    {
      "LGJCPENNFBC": 803,
      "OBDBAJHHNDI": 803,
      "OIGJHKMMBLD": 3,
      "PEFDOIHIIBG": 2,
      "BFBNEHIIGKB": [
        1,
        4,
        3
      ],
      "HBNHAKJHDJC": 5,
      "DBLDBAJDLBP": 7,
      "EOCOOJDFMLJ": 5
    },
    {
      "LGJCPENNFBC": 804,
      "OBDBAJHHNDI": 804,
      "OIGJHKMMBLD": 3,
      "PEFDOIHIIBG": 2,
      "BFBNEHIIGKB": [
        1,
        5,
        6
      ],
      "HBNHAKJHDJC": 4,
      "DBLDBAJDLBP": 7,
      "EOCOOJDFMLJ": 5
    },
    {
      "LGJCPENNFBC": 805,
      "OBDBAJHHNDI": 805,
      "OIGJHKMMBLD": 3,
      "PEFDOIHIIBG": 2,
      "BFBNEHIIGKB": [
        1,
        4,
        3
      ],
      "HBNHAKJHDJC": 6,
      "DBLDBAJDLBP": 7,
      "EOCOOJDFMLJ": 5
    },
    {
      "LGJCPENNFBC": 806,
      "OBDBAJHHNDI": 806,
      "OIGJHKMMBLD": 3,
      "PEFDOIHIIBG": 2,
      "BFBNEHIIGKB": [
        1,
        2,
        3
      ],
      "HBNHAKJHDJC": 7,
      "DBLDBAJDLBP": 8,
      "EOCOOJDFMLJ": 6
    },
    {
      "LGJCPENNFBC": 807,
      "OBDBAJHHNDI": 807,
      "OIGJHKMMBLD": 3,
      "PEFDOIHIIBG": 2,
      "BFBNEHIIGKB": [
        1,
        5,
        6
      ],
      "HBNHAKJHDJC": 1,
      "DBLDBAJDLBP": 8,
      "EOCOOJDFMLJ": 6
    },
    {
      "LGJCPENNFBC": 808,
      "OBDBAJHHNDI": 808,
      "OIGJHKMMBLD": 2,
      "PEFDOIHIIBG": 1,
      "BFBNEHIIGKB": [
        1,
        4,
        3
      ],
      "HBNHAKJHDJC": 2,
      "DBLDBAJDLBP": 8,
      "EOCOOJDFMLJ": 6
    },
    {
      "LGJCPENNFBC": 809,
      "OBDBAJHHNDI": 809,
      "OIGJHKMMBLD": 2,
      "PEFDOIHIIBG": 1,
      "BFBNEHIIGKB": [
        1,
        5,
        6
      ],
      "HBNHAKJHDJC": 5,
      "DBLDBAJDLBP": 8,
      "EOCOOJDFMLJ": 6
    },
    {
      "LGJCPENNFBC": 840,
      "OBDBAJHHNDI": 840,
      "OIGJHKMMBLD": 2,
      "PEFDOIHIIBG": 1,
      "BFBNEHIIGKB": [
        1,
        4,
        3
      ],
      "HBNHAKJHDJC": 4,
      "DBLDBAJDLBP": 8,
      "EOCOOJDFMLJ": 6
    },
    {
      "LGJCPENNFBC": 841,
      "OBDBAJHHNDI": 841,
      "OIGJHKMMBLD": 2,
      "PEFDOIHIIBG": 1,
      "BFBNEHIIGKB": [
        1,
        2,
        3
      ],
      "HBNHAKJHDJC": 6,
      "DBLDBAJDLBP": 9,
      "EOCOOJDFMLJ": 7
    },
    {
      "LGJCPENNFBC": 842,
      "OBDBAJHHNDI": 842,
      "OIGJHKMMBLD": 2,
      "PEFDOIHIIBG": 1,
      "BFBNEHIIGKB": [
        1,
        5,
        6
      ],
      "HBNHAKJHDJC": 13,
      "DBLDBAJDLBP": 9,
      "EOCOOJDFMLJ": 7
    },
    {
      "LGJCPENNFBC": 843,
      "OBDBAJHHNDI": 827,
      "OIGJHKMMBLD": 2,
      "PEFDOIHIIBG": 1,
      "BFBNEHIIGKB": [
        1,
        5,
        6
      ],
      "HBNHAKJHDJC": 5,
      "DBLDBAJDLBP": 9,
      "EOCOOJDFMLJ": 7
    },
    {
      "LGJCPENNFBC": 844,
      "OBDBAJHHNDI": 828,
      "OIGJHKMMBLD": 2,
      "PEFDOIHIIBG": 1,
      "BFBNEHIIGKB": [
        1,
        4,
        3
      ],
      "HBNHAKJHDJC": 4,
      "DBLDBAJDLBP": 9,
      "EOCOOJDFMLJ": 7
    },
    {
      "LGJCPENNFBC": 845,
      "OBDBAJHHNDI": 829,
      "OIGJHKMMBLD": 2,
      "PEFDOIHIIBG": 1,
      "BFBNEHIIGKB": [
        1,
        5,
        6
      ],
      "HBNHAKJHDJC": 6,
      "DBLDBAJDLBP": 9,
      "EOCOOJDFMLJ": 7
    },
    {
      "LGJCPENNFBC": 846,
      "OBDBAJHHNDI": 830,
      "OIGJHKMMBLD": 2,
      "PEFDOIHIIBG": 1,
      "BFBNEHIIGKB": [
        1,
        4,
        3
      ],
      "HBNHAKJHDJC": 11,
      "DBLDBAJDLBP": 9,
      "EOCOOJDFMLJ": 7
    },
    {
      "LGJCPENNFBC": 847,
      "OBDBAJHHNDI": 831,
      "OIGJHKMMBLD": 1,
      "PEFDOIHIIBG": 1,
      "BFBNEHIIGKB": [
        1,
        2,
        3
      ],
      "HBNHAKJHDJC": 1,
      "DBLDBAJDLBP": 7,
      "EOCOOJDFMLJ": 5
    },
    {
      "LGJCPENNFBC": 848,
      "OBDBAJHHNDI": 832,
      "OIGJHKMMBLD": 1,
      "PEFDOIHIIBG": 1,
      "BFBNEHIIGKB": [
        1,
        5,
        6
      ],
      "HBNHAKJHDJC": 2,
      "DBLDBAJDLBP": 7,
      "EOCOOJDFMLJ": 5
    },
    {
      "LGJCPENNFBC": 849,
      "OBDBAJHHNDI": 833,
      "OIGJHKMMBLD": 3,
      "PEFDOIHIIBG": 2,
      "BFBNEHIIGKB": [
        1,
        4,
        3
      ],
      "HBNHAKJHDJC": 5,
      "DBLDBAJDLBP": 7,
      "EOCOOJDFMLJ": 5
    },
    {
      "LGJCPENNFBC": 860,
      "OBDBAJHHNDI": 840,
      "OIGJHKMMBLD": 2,
      "PEFDOIHIIBG": 1,
      "BFBNEHIIGKB": [
        1,
        4,
        3
      ],
      "HBNHAKJHDJC": 4,
      "DBLDBAJDLBP": 8,
      "EOCOOJDFMLJ": 6
    },
    {
      "LGJCPENNFBC": 861,
      "OBDBAJHHNDI": 841,
      "OIGJHKMMBLD": 2,
      "PEFDOIHIIBG": 1,
      "BFBNEHIIGKB": [
        1,
        2,
        3
      ],
      "HBNHAKJHDJC": 6,
      "DBLDBAJDLBP": 9,
      "EOCOOJDFMLJ": 7
    },
    {
      "LGJCPENNFBC": 862,
      "OBDBAJHHNDI": 842,
      "OIGJHKMMBLD": 2,
      "PEFDOIHIIBG": 1,
      "BFBNEHIIGKB": [
        1,
        5,
        6
      ],
      "HBNHAKJHDJC": 13,
      "DBLDBAJDLBP": 9,
      "EOCOOJDFMLJ": 7
    },
    {
      "LGJCPENNFBC": 863,
      "OBDBAJHHNDI": 827,
      "OIGJHKMMBLD": 2,
      "PEFDOIHIIBG": 1,
      "BFBNEHIIGKB": [
        1,
        5,
        6
      ],
      "HBNHAKJHDJC": 5,
      "DBLDBAJDLBP": 9,
      "EOCOOJDFMLJ": 7
    },
    {
      "LGJCPENNFBC": 864,
      "OBDBAJHHNDI": 828,
      "OIGJHKMMBLD": 2,
      "PEFDOIHIIBG": 1,
      "BFBNEHIIGKB": [
        1,
        4,
        3
      ],
      "HBNHAKJHDJC": 4,
      "DBLDBAJDLBP": 9,
      "EOCOOJDFMLJ": 7
    },
    {
      "LGJCPENNFBC": 865,
      "OBDBAJHHNDI": 829,
      "OIGJHKMMBLD": 2,
      "PEFDOIHIIBG": 1,
      "BFBNEHIIGKB": [
        1,
        5,
        6
      ],
      "HBNHAKJHDJC": 6,
      "DBLDBAJDLBP": 9,
      "EOCOOJDFMLJ": 7
    },
    {
      "LGJCPENNFBC": 866,
      "OBDBAJHHNDI": 830,
      "OIGJHKMMBLD": 2,
      "PEFDOIHIIBG": 1,
      "BFBNEHIIGKB": [
        1,
        4,
        3
      ],
      "HBNHAKJHDJC": 11,
      "DBLDBAJDLBP": 9,
      "EOCOOJDFMLJ": 7
    },
    {
      "LGJCPENNFBC": 867,
      "OBDBAJHHNDI": 831,
      "OIGJHKMMBLD": 1,
      "PEFDOIHIIBG": 1,
      "BFBNEHIIGKB": [
        1,
        2,
        3
      ],
      "HBNHAKJHDJC": 1,
      "DBLDBAJDLBP": 9,
      "EOCOOJDFMLJ": 7
    },
    {
      "LGJCPENNFBC": 868,
      "OBDBAJHHNDI": 832,
      "OIGJHKMMBLD": 1,
      "PEFDOIHIIBG": 1,
      "BFBNEHIIGKB": [
        1,
        5,
        6
      ],
      "HBNHAKJHDJC": 2,
      "DBLDBAJDLBP": 9,
      "EOCOOJDFMLJ": 7
    },
    {
      "LGJCPENNFBC": 869,
      "OBDBAJHHNDI": 833,
      "OIGJHKMMBLD": 3,
      "PEFDOIHIIBG": 2,
      "BFBNEHIIGKB": [
        1,
        4,
        3
      ],
      "HBNHAKJHDJC": 5,
      "DBLDBAJDLBP": 9,
      "EOCOOJDFMLJ": 7
    },
    {
      "LGJCPENNFBC": 101,
      "OBDBAJHHNDI": 101,
      "OIGJHKMMBLD": 1,
      "PEFDOIHIIBG": 1,
      "BFBNEHIIGKB": [
        1,
        3
      ],
      "HBNHAKJHDJC": 2,
      "DBLDBAJDLBP": 6,
      "EOCOOJDFMLJ": 5
    },
    {
      "LGJCPENNFBC": 102,
      "OBDBAJHHNDI": 102,
      "OIGJHKMMBLD": 1,
      "PEFDOIHIIBG": 1,
      "BFBNEHIIGKB": [
        2,
        3
      ],
      "HBNHAKJHDJC": 1,
      "DBLDBAJDLBP": 6,
      "EOCOOJDFMLJ": 5
    },
    {
      "LGJCPENNFBC": 103,
      "OBDBAJHHNDI": 103,
      "OIGJHKMMBLD": 3,
      "PEFDOIHIIBG": 2,
      "BFBNEHIIGKB": [
        1,
        3
      ],
      "HBNHAKJHDJC": 2,
      "DBLDBAJDLBP": 6,
      "EOCOOJDFMLJ": 5
    },
    {
      "LGJCPENNFBC": 104,
      "OBDBAJHHNDI": 104,
      "OIGJHKMMBLD": 3,
      "PEFDOIHIIBG": 2,
      "BFBNEHIIGKB": [
        2,
        3
      ],
      "HBNHAKJHDJC": 1,
      "DBLDBAJDLBP": 6,
      "EOCOOJDFMLJ": 5
    },
    {
      "LGJCPENNFBC": 105,
      "OBDBAJHHNDI": 105,
      "OIGJHKMMBLD": 3,
      "PEFDOIHIIBG": 2,
      "BFBNEHIIGKB": [
        1,
        3
      ],
      "HBNHAKJHDJC": 601,
      "DBLDBAJDLBP": 6,
      "EOCOOJDFMLJ": 5
    },
    {
      "LGJCPENNFBC": 106,
      "OBDBAJHHNDI": 106,
      "OIGJHKMMBLD": 3,
      "PEFDOIHIIBG": 2,
      "BFBNEHIIGKB": [
        2,
        3
      ],
      "HBNHAKJHDJC": 3,
      "DBLDBAJDLBP": 7,
      "EOCOOJDFMLJ": 5
    },
    {
      "LGJCPENNFBC": 107,
      "OBDBAJHHNDI": 107,
      "OIGJHKMMBLD": 3,
      "PEFDOIHIIBG": 2,
      "BFBNEHIIGKB": [
        1,
        3
      ],
      "HBNHAKJHDJC": 1,
      "DBLDBAJDLBP": 7,
      "EOCOOJDFMLJ": 5
    },
    {
      "LGJCPENNFBC": 108,
      "OBDBAJHHNDI": 108,
      "OIGJHKMMBLD": 2,
      "PEFDOIHIIBG": 1,
      "BFBNEHIIGKB": [
        2,
        3
      ],
      "HBNHAKJHDJC": 2,
      "DBLDBAJDLBP": 7,
      "EOCOOJDFMLJ": 5
    },
    {
      "LGJCPENNFBC": 109,
      "OBDBAJHHNDI": 109,
      "OIGJHKMMBLD": 2,
      "PEFDOIHIIBG": 1,
      "BFBNEHIIGKB": [
        1,
        3
      ],
      "HBNHAKJHDJC": 1,
      "DBLDBAJDLBP": 8,
      "EOCOOJDFMLJ": 6
    },
    {
      "LGJCPENNFBC": 401,
      "OBDBAJHHNDI": 401,
      "OIGJHKMMBLD": 1,
      "PEFDOIHIIBG": 1,
      "BFBNEHIIGKB": [
        2,
        3
      ],
      "HBNHAKJHDJC": 4,
      "DBLDBAJDLBP": 3,
      "EOCOOJDFMLJ": 3
    },
    {
      "LGJCPENNFBC": 402,
      "OBDBAJHHNDI": 402,
      "OIGJHKMMBLD": 1,
      "PEFDOIHIIBG": 1,
      "BFBNEHIIGKB": [
        1,
        4
      ],
      "HBNHAKJHDJC": 6,
      "DBLDBAJDLBP": 3,
      "EOCOOJDFMLJ": 3
    },
    {
      "LGJCPENNFBC": 403,
      "OBDBAJHHNDI": 403,
      "OIGJHKMMBLD": 1,
      "PEFDOIHIIBG": 1,
      "BFBNEHIIGKB": [
        1,
        5
      ],
      "HBNHAKJHDJC": 9,
      "DBLDBAJDLBP": 3,
      "EOCOOJDFMLJ": 3
    },
    {
      "LGJCPENNFBC": 404,
      "OBDBAJHHNDI": 404,
      "OIGJHKMMBLD": 3,
      "PEFDOIHIIBG": 2,
      "BFBNEHIIGKB": [
        2,
        5
      ],
      "HBNHAKJHDJC": 4,
      "DBLDBAJDLBP": 3,
      "EOCOOJDFMLJ": 3
    },
    {
      "LGJCPENNFBC": 405,
      "OBDBAJHHNDI": 405,
      "OIGJHKMMBLD": 3,
      "PEFDOIHIIBG": 2,
      "BFBNEHIIGKB": [
        1,
        4,
        3
      ],
      "HBNHAKJHDJC": 6,
      "DBLDBAJDLBP": 7,
      "EOCOOJDFMLJ": 5
    },
    {
      "LGJCPENNFBC": 406,
      "OBDBAJHHNDI": 406,
      "OIGJHKMMBLD": 3,
      "PEFDOIHIIBG": 2,
      "BFBNEHIIGKB": [
        1,
        2,
        3
      ],
      "HBNHAKJHDJC": 11,
      "DBLDBAJDLBP": 8,
      "EOCOOJDFMLJ": 6
    },
    {
      "LGJCPENNFBC": 407,
      "OBDBAJHHNDI": 407,
      "OIGJHKMMBLD": 3,
      "PEFDOIHIIBG": 2,
      "BFBNEHIIGKB": [
        1,
        5,
        6
      ],
      "HBNHAKJHDJC": 9,
      "DBLDBAJDLBP": 8,
      "EOCOOJDFMLJ": 6
    },
    {
      "LGJCPENNFBC": 408,
      "OBDBAJHHNDI": 408,
      "OIGJHKMMBLD": 2,
      "PEFDOIHIIBG": 1,
      "BFBNEHIIGKB": [
        1,
        4,
        3
      ],
      "HBNHAKJHDJC": 4,
      "DBLDBAJDLBP": 8,
      "EOCOOJDFMLJ": 6
    },
    {
      "LGJCPENNFBC": 409,
      "OBDBAJHHNDI": 409,
      "OIGJHKMMBLD": 2,
      "PEFDOIHIIBG": 1,
      "BFBNEHIIGKB": [
        1,
        5,
        6
      ],
      "HBNHAKJHDJC": 7,
      "DBLDBAJDLBP": 8,
      "EOCOOJDFMLJ": 6
    },
    {
      "LGJCPENNFBC": 410,
      "OBDBAJHHNDI": 410,
      "OIGJHKMMBLD": 2,
      "PEFDOIHIIBG": 1,
      "BFBNEHIIGKB": [
        1,
        4,
        3
      ],
      "HBNHAKJHDJC": 12,
      "DBLDBAJDLBP": 8,
      "EOCOOJDFMLJ": 6
    },
    {
      "LGJCPENNFBC": 411,
      "OBDBAJHHNDI": 411,
      "OIGJHKMMBLD": 2,
      "PEFDOIHIIBG": 1,
      "BFBNEHIIGKB": [
        1,
        2,
        3
      ],
      "HBNHAKJHDJC": 4,
      "DBLDBAJDLBP": 9,
      "EOCOOJDFMLJ": 7
    },
    {
      "LGJCPENNFBC": 412,
      "OBDBAJHHNDI": 412,
      "OIGJHKMMBLD": 2,
      "PEFDOIHIIBG": 1,
      "BFBNEHIIGKB": [
        1,
        5,
        6
      ],
      "HBNHAKJHDJC": 7,
      "DBLDBAJDLBP": 9,
      "EOCOOJDFMLJ": 7
    },
    {
      "LGJCPENNFBC": 413,
      "OBDBAJHHNDI": 413,
      "OIGJHKMMBLD": 2,
      "PEFDOIHIIBG": 1,
      "BFBNEHIIGKB": [
        1,
        4,
        3
      ],
      "HBNHAKJHDJC": 6,
      "DBLDBAJDLBP": 9,
      "EOCOOJDFMLJ": 7
    },
    {
      "LGJCPENNFBC": 414,
      "OBDBAJHHNDI": 414,
      "OIGJHKMMBLD": 2,
      "PEFDOIHIIBG": 1,
      "BFBNEHIIGKB": [
        1,
        5,
        6
      ],
      "HBNHAKJHDJC": 4,
      "DBLDBAJDLBP": 9,
      "EOCOOJDFMLJ": 7
    },
    {
      "LGJCPENNFBC": 415,
      "OBDBAJHHNDI": 415,
      "OIGJHKMMBLD": 2,
      "PEFDOIHIIBG": 1,
      "BFBNEHIIGKB": [
        1,
        4,
        3
      ],
      "HBNHAKJHDJC": 9,
      "DBLDBAJDLBP": 9,
      "EOCOOJDFMLJ": 7
    },
    {
      "LGJCPENNFBC": 850,
      "OBDBAJHHNDI": 834,
      "OIGJHKMMBLD": 3,
      "PEFDOIHIIBG": 2,
      "BFBNEHIIGKB": [
        1,
        5,
        6
      ],
      "HBNHAKJHDJC": 4,
      "DBLDBAJDLBP": 7,
      "EOCOOJDFMLJ": 5
    },
    {
      "LGJCPENNFBC": 851,
      "OBDBAJHHNDI": 835,
      "OIGJHKMMBLD": 3,
      "PEFDOIHIIBG": 2,
      "BFBNEHIIGKB": [
        1,
        4,
        3
      ],
      "HBNHAKJHDJC": 6,
      "DBLDBAJDLBP": 7,
      "EOCOOJDFMLJ": 5
    },
    {
      "LGJCPENNFBC": 852,
      "OBDBAJHHNDI": 836,
      "OIGJHKMMBLD": 3,
      "PEFDOIHIIBG": 2,
      "BFBNEHIIGKB": [
        1,
        2,
        3
      ],
      "HBNHAKJHDJC": 12,
      "DBLDBAJDLBP": 8,
      "EOCOOJDFMLJ": 6
    },
    {
      "LGJCPENNFBC": 853,
      "OBDBAJHHNDI": 837,
      "OIGJHKMMBLD": 3,
      "PEFDOIHIIBG": 2,
      "BFBNEHIIGKB": [
        1,
        5,
        6
      ],
      "HBNHAKJHDJC": 1,
      "DBLDBAJDLBP": 8,
      "EOCOOJDFMLJ": 6
    },
    {
      "LGJCPENNFBC": 854,
      "OBDBAJHHNDI": 838,
      "OIGJHKMMBLD": 2,
      "PEFDOIHIIBG": 1,
      "BFBNEHIIGKB": [
        1,
        4,
        3
      ],
      "HBNHAKJHDJC": 2,
      "DBLDBAJDLBP": 8,
      "EOCOOJDFMLJ": 6
    },
    {
      "LGJCPENNFBC": 855,
      "OBDBAJHHNDI": 839,
      "OIGJHKMMBLD": 2,
      "PEFDOIHIIBG": 1,
      "BFBNEHIIGKB": [
        1,
        5,
        6
      ],
      "HBNHAKJHDJC": 5,
      "DBLDBAJDLBP": 8,
      "EOCOOJDFMLJ": 6
    },
    {
      "LGJCPENNFBC": 856,
      "OBDBAJHHNDI": 840,
      "OIGJHKMMBLD": 2,
      "PEFDOIHIIBG": 1,
      "BFBNEHIIGKB": [
        1,
        4,
        3
      ],
      "HBNHAKJHDJC": 4,
      "DBLDBAJDLBP": 8,
      "EOCOOJDFMLJ": 6
    },
    {
      "LGJCPENNFBC": 857,
      "OBDBAJHHNDI": 841,
      "OIGJHKMMBLD": 2,
      "PEFDOIHIIBG": 1,
      "BFBNEHIIGKB": [
        1,
        2,
        3
      ],
      "HBNHAKJHDJC": 6,
      "DBLDBAJDLBP": 9,
      "EOCOOJDFMLJ": 7
    },
    {
      "LGJCPENNFBC": 858,
      "OBDBAJHHNDI": 842,
      "OIGJHKMMBLD": 2,
      "PEFDOIHIIBG": 1,
      "BFBNEHIIGKB": [
        1,
        5,
        6
      ],
      "HBNHAKJHDJC": 13,
      "DBLDBAJDLBP": 9,
      "EOCOOJDFMLJ": 7
    },
    {
      "LGJCPENNFBC": 859,
      "OBDBAJHHNDI": 839,
      "OIGJHKMMBLD": 2,
      "PEFDOIHIIBG": 1,
      "BFBNEHIIGKB": [
        1,
        5,
        6
      ],
      "HBNHAKJHDJC": 5,
      "DBLDBAJDLBP": 8,
      "EOCOOJDFMLJ": 6
    },
    {
      "LGJCPENNFBC": 870,
      "OBDBAJHHNDI": 834,
      "OIGJHKMMBLD": 3,
      "PEFDOIHIIBG": 2,
      "BFBNEHIIGKB": [
        1,
        5,
        6
      ],
      "HBNHAKJHDJC": 4,
      "DBLDBAJDLBP": 9,
      "EOCOOJDFMLJ": 7
    },
    {
      "LGJCPENNFBC": 871,
      "OBDBAJHHNDI": 835,
      "OIGJHKMMBLD": 3,
      "PEFDOIHIIBG": 2,
      "BFBNEHIIGKB": [
        1,
        4,
        3
      ],
      "HBNHAKJHDJC": 6,
      "DBLDBAJDLBP": 9,
      "EOCOOJDFMLJ": 7
    },
    {
      "LGJCPENNFBC": 872,
      "OBDBAJHHNDI": 836,
      "OIGJHKMMBLD": 3,
      "PEFDOIHIIBG": 2,
      "BFBNEHIIGKB": [
        1,
        2,
        3
      ],
      "HBNHAKJHDJC": 12,
      "DBLDBAJDLBP": 9,
      "EOCOOJDFMLJ": 7
    },
    {
      "LGJCPENNFBC": 873,
      "OBDBAJHHNDI": 837,
      "OIGJHKMMBLD": 3,
      "PEFDOIHIIBG": 2,
      "BFBNEHIIGKB": [
        1,
        5,
        6
      ],
      "HBNHAKJHDJC": 1,
      "DBLDBAJDLBP": 9,
      "EOCOOJDFMLJ": 7
    },
    {
      "LGJCPENNFBC": 874,
      "OBDBAJHHNDI": 838,
      "OIGJHKMMBLD": 2,
      "PEFDOIHIIBG": 1,
      "BFBNEHIIGKB": [
        1,
        4,
        3
      ],
      "HBNHAKJHDJC": 2,
      "DBLDBAJDLBP": 9,
      "EOCOOJDFMLJ": 7
    },
    {
      "LGJCPENNFBC": 875,
      "OBDBAJHHNDI": 839,
      "OIGJHKMMBLD": 2,
      "PEFDOIHIIBG": 1,
      "BFBNEHIIGKB": [
        1,
        5,
        6
      ],
      "HBNHAKJHDJC": 5,
      "DBLDBAJDLBP": 9,
      "EOCOOJDFMLJ": 7
    },
    {
      "LGJCPENNFBC": 876,
      "OBDBAJHHNDI": 840,
      "OIGJHKMMBLD": 2,
      "PEFDOIHIIBG": 1,
      "BFBNEHIIGKB": [
        1,
        4,
        3
      ],
      "HBNHAKJHDJC": 4,
      "DBLDBAJDLBP": 9,
      "EOCOOJDFMLJ": 7
    },
    {
      "LGJCPENNFBC": 877,
      "OBDBAJHHNDI": 841,
      "OIGJHKMMBLD": 2,
      "PEFDOIHIIBG": 1,
      "BFBNEHIIGKB": [
        1,
        2,
        3
      ],
      "HBNHAKJHDJC": 6,
      "DBLDBAJDLBP": 9,
      "EOCOOJDFMLJ": 7
    },
    {
      "LGJCPENNFBC": 878,
      "OBDBAJHHNDI": 842,
      "OIGJHKMMBLD": 2,
      "PEFDOIHIIBG": 1,
      "BFBNEHIIGKB": [
        1,
        5,
        6
      ],
      "HBNHAKJHDJC": 13,
      "DBLDBAJDLBP": 9,
      "EOCOOJDFMLJ": 7
    },
    {
      "LGJCPENNFBC": 201,
      "OBDBAJHHNDI": 201,
      "OIGJHKMMBLD": 1,
      "PEFDOIHIIBG": 1,
      "BFBNEHIIGKB": [
        1,
        3
      ],
      "HBNHAKJHDJC": 2,
      "DBLDBAJDLBP": 6,
      "EOCOOJDFMLJ": 5
    },
    {
      "LGJCPENNFBC": 202,
      "OBDBAJHHNDI": 202,
      "OIGJHKMMBLD": 1,
      "PEFDOIHIIBG": 1,
      "BFBNEHIIGKB": [
        2,
        3
      ],
      "HBNHAKJHDJC": 4,
      "DBLDBAJDLBP": 6,
      "EOCOOJDFMLJ": 5
    },
    {
      "LGJCPENNFBC": 203,
      "OBDBAJHHNDI": 203,
      "OIGJHKMMBLD": 1,
      "PEFDOIHIIBG": 1,
      "BFBNEHIIGKB": [
        1,
        3
      ],
      "HBNHAKJHDJC": 601,
      "DBLDBAJDLBP": 6,
      "EOCOOJDFMLJ": 5
    },
    {
      "LGJCPENNFBC": 204,
      "OBDBAJHHNDI": 204,
      "OIGJHKMMBLD": 3,
      "PEFDOIHIIBG": 2,
      "BFBNEHIIGKB": [
        2,
        5
      ],
      "HBNHAKJHDJC": 4,
      "DBLDBAJDLBP": 6,
      "EOCOOJDFMLJ": 5
    },
    {
      "LGJCPENNFBC": 205,
      "OBDBAJHHNDI": 205,
      "OIGJHKMMBLD": 3,
      "PEFDOIHIIBG": 2,
      "BFBNEHIIGKB": [
        1,
        3,
        5
      ],
      "HBNHAKJHDJC": 2,
      "DBLDBAJDLBP": 6,
      "EOCOOJDFMLJ": 5
    },
    {
      "LGJCPENNFBC": 206,
      "OBDBAJHHNDI": 206,
      "OIGJHKMMBLD": 3,
      "PEFDOIHIIBG": 2,
      "BFBNEHIIGKB": [
        2,
        3,
        5
      ],
      "HBNHAKJHDJC": 7,
      "DBLDBAJDLBP": 6,
      "EOCOOJDFMLJ": 5
    },
    {
      "LGJCPENNFBC": 207,
      "OBDBAJHHNDI": 207,
      "OIGJHKMMBLD": 3,
      "PEFDOIHIIBG": 2,
      "BFBNEHIIGKB": [
        1,
        2,
        3
      ],
      "HBNHAKJHDJC": 4,
      "DBLDBAJDLBP": 7,
      "EOCOOJDFMLJ": 5
    },
    {
      "LGJCPENNFBC": 208,
      "OBDBAJHHNDI": 208,
      "OIGJHKMMBLD": 2,
      "PEFDOIHIIBG": 1,
      "BFBNEHIIGKB": [
        1,
        2,
        3
      ],
      "HBNHAKJHDJC": 2,
      "DBLDBAJDLBP": 7,
      "EOCOOJDFMLJ": 5
    },
    {
      "LGJCPENNFBC": 209,
      "OBDBAJHHNDI": 209,
      "OIGJHKMMBLD": 2,
      "PEFDOIHIIBG": 1,
      "BFBNEHIIGKB": [
        1,
        2,
        3
      ],
      "HBNHAKJHDJC": 4,
      "DBLDBAJDLBP": 8,
      "EOCOOJDFMLJ": 6
    },
    {
      "LGJCPENNFBC": 310,
      "OBDBAJHHNDI": 310,
      "OIGJHKMMBLD": 2,
      "PEFDOIHIIBG": 1,
      "BFBNEHIIGKB": [
        2,
        4,
        5
      ],
      "HBNHAKJHDJC": 11,
      "DBLDBAJDLBP": 8,
      "EOCOOJDFMLJ": 6
    },
    {
      "LGJCPENNFBC": 311,
      "OBDBAJHHNDI": 311,
      "OIGJHKMMBLD": 2,
      "PEFDOIHIIBG": 1,
      "BFBNEHIIGKB": [
        1,
        3
      ],
      "HBNHAKJHDJC": 6,
      "DBLDBAJDLBP": 9,
      "EOCOOJDFMLJ": 7
    },
    {
      "LGJCPENNFBC": 312,
      "OBDBAJHHNDI": 312,
      "OIGJHKMMBLD": 2,
      "PEFDOIHIIBG": 1,
      "BFBNEHIIGKB": [
        2,
        5,
        3
      ],
      "HBNHAKJHDJC": 2,
      "DBLDBAJDLBP": 9,
      "EOCOOJDFMLJ": 7
    },
    {
      "LGJCPENNFBC": 313,
      "OBDBAJHHNDI": 313,
      "OIGJHKMMBLD": 2,
      "PEFDOIHIIBG": 1,
      "BFBNEHIIGKB": [
        1,
        5,
        4
      ],
      "HBNHAKJHDJC": 4,
      "DBLDBAJDLBP": 9,
      "EOCOOJDFMLJ": 7
    },
    {
      "LGJCPENNFBC": 314,
      "OBDBAJHHNDI": 314,
      "OIGJHKMMBLD": 2,
      "PEFDOIHIIBG": 1,
      "BFBNEHIIGKB": [
        1,
        3,
        6
      ],
      "HBNHAKJHDJC": 6,
      "DBLDBAJDLBP": 9,
      "EOCOOJDFMLJ": 7
    },
    {
      "LGJCPENNFBC": 315,
      "OBDBAJHHNDI": 315,
      "OIGJHKMMBLD": 2,
      "PEFDOIHIIBG": 1,
      "BFBNEHIIGKB": [
        2,
        4,
        5
      ],
      "HBNHAKJHDJC": 11,
      "DBLDBAJDLBP": 9,
      "EOCOOJDFMLJ": 7
    },
    {
      "LGJCPENNFBC": 501,
      "OBDBAJHHNDI": 501,
      "OIGJHKMMBLD": 1,
      "PEFDOIHIIBG": 1,
      "BFBNEHIIGKB": [
        1,
        2,
        3
      ],
      "HBNHAKJHDJC": 4,
      "DBLDBAJDLBP": 7,
      "EOCOOJDFMLJ": 5
    },
    {
      "LGJCPENNFBC": 502,
      "OBDBAJHHNDI": 502,
      "OIGJHKMMBLD": 1,
      "PEFDOIHIIBG": 1,
      "BFBNEHIIGKB": [
        1,
        4,
        5
      ],
      "HBNHAKJHDJC": 6,
      "DBLDBAJDLBP": 7,
      "EOCOOJDFMLJ": 5
    },
    {
      "LGJCPENNFBC": 503,
      "OBDBAJHHNDI": 503,
      "OIGJHKMMBLD": 1,
      "PEFDOIHIIBG": 1,
      "BFBNEHIIGKB": [
        1,
        2,
        6
      ],
      "HBNHAKJHDJC": 10,
      "DBLDBAJDLBP": 7,
      "EOCOOJDFMLJ": 5
    },
    {
      "LGJCPENNFBC": 504,
      "OBDBAJHHNDI": 504,
      "OIGJHKMMBLD": 3,
      "PEFDOIHIIBG": 2,
      "BFBNEHIIGKB": [
        1,
        5,
        6
      ],
      "HBNHAKJHDJC": 4,
      "DBLDBAJDLBP": 7,
      "EOCOOJDFMLJ": 5
    },
    {
      "LGJCPENNFBC": 505,
      "OBDBAJHHNDI": 505,
      "OIGJHKMMBLD": 3,
      "PEFDOIHIIBG": 2,
      "BFBNEHIIGKB": [
        1,
        4,
        3
      ],
      "HBNHAKJHDJC": 6,
      "DBLDBAJDLBP": 7,
      "EOCOOJDFMLJ": 5
    },
    {
      "LGJCPENNFBC": 506,
      "OBDBAJHHNDI": 506,
      "OIGJHKMMBLD": 3,
      "PEFDOIHIIBG": 2,
      "BFBNEHIIGKB": [
        1,
        2,
        3
      ],
      "HBNHAKJHDJC": 12,
      "DBLDBAJDLBP": 8,
      "EOCOOJDFMLJ": 6
    },
    {
      "LGJCPENNFBC": 507,
      "OBDBAJHHNDI": 507,
      "OIGJHKMMBLD": 3,
      "PEFDOIHIIBG": 2,
      "BFBNEHIIGKB": [
        1,
        5,
        6
      ],
      "HBNHAKJHDJC": 11,
      "DBLDBAJDLBP": 8,
      "EOCOOJDFMLJ": 6
    },
    {
      "LGJCPENNFBC": 508,
      "OBDBAJHHNDI": 508,
      "OIGJHKMMBLD": 2,
      "PEFDOIHIIBG": 1,
      "BFBNEHIIGKB": [
        1,
        4,
        3
      ],
      "HBNHAKJHDJC": 7,
      "DBLDBAJDLBP": 8,
      "EOCOOJDFMLJ": 6
    },
    {
      "LGJCPENNFBC": 509,
      "OBDBAJHHNDI": 509,
      "OIGJHKMMBLD": 2,
      "PEFDOIHIIBG": 1,
      "BFBNEHIIGKB": [
        1,
        5,
        6
      ],
      "HBNHAKJHDJC": 4,
      "DBLDBAJDLBP": 8,
      "EOCOOJDFMLJ": 6
    },
    {
      "LGJCPENNFBC": 610,
      "OBDBAJHHNDI": 610,
      "OIGJHKMMBLD": 2,
      "PEFDOIHIIBG": 1,
      "BFBNEHIIGKB": [
        1,
        4,
        3
      ],
      "HBNHAKJHDJC": 12,
      "DBLDBAJDLBP": 8,
      "EOCOOJDFMLJ": 6
    },
    {
      "LGJCPENNFBC": 611,
      "OBDBAJHHNDI": 611,
      "OIGJHKMMBLD": 2,
      "PEFDOIHIIBG": 1,
      "BFBNEHIIGKB": [
        1,
        2,
        3
      ],
      "HBNHAKJHDJC": 2,
      "DBLDBAJDLBP": 9,
      "EOCOOJDFMLJ": 7
    },
    {
      "LGJCPENNFBC": 612,
      "OBDBAJHHNDI": 612,
      "OIGJHKMMBLD": 2,
      "PEFDOIHIIBG": 1,
      "BFBNEHIIGKB": [
        1,
        5,
        6
      ],
      "HBNHAKJHDJC": 6,
      "DBLDBAJDLBP": 9,
      "EOCOOJDFMLJ": 7
    },
    {
      "LGJCPENNFBC": 613,
      "OBDBAJHHNDI": 613,
      "OIGJHKMMBLD": 2,
      "PEFDOIHIIBG": 1,
      "BFBNEHIIGKB": [
        1,
        4,
        3
      ],
      "HBNHAKJHDJC": 4,
      "DBLDBAJDLBP": 9,
      "EOCOOJDFMLJ": 7
    },
    {
      "LGJCPENNFBC": 614,
      "OBDBAJHHNDI": 614,
      "OIGJHKMMBLD": 2,
      "PEFDOIHIIBG": 1,
      "BFBNEHIIGKB": [
        1,
        5,
        6
      ],
      "HBNHAKJHDJC": 2,
      "DBLDBAJDLBP": 9,
      "EOCOOJDFMLJ": 7
    },
    {
      "LGJCPENNFBC": 615,
      "OBDBAJHHNDI": 615,
      "OIGJHKMMBLD": 2,
      "PEFDOIHIIBG": 1,
      "BFBNEHIIGKB": [
        1,
        4,
        3
      ],
      "HBNHAKJHDJC": 12,
      "DBLDBAJDLBP": 9,
      "EOCOOJDFMLJ": 7
    },
    {
      "LGJCPENNFBC": 701,
      "OBDBAJHHNDI": 701,
      "OIGJHKMMBLD": 1,
      "PEFDOIHIIBG": 1,
      "BFBNEHIIGKB": [
        1,
        2,
        3
      ],
      "HBNHAKJHDJC": 4,
      "DBLDBAJDLBP": 7,
      "EOCOOJDFMLJ": 5
    },
    {
      "LGJCPENNFBC": 702,
      "OBDBAJHHNDI": 702,
      "OIGJHKMMBLD": 1,
      "PEFDOIHIIBG": 1,
      "BFBNEHIIGKB": [
        1,
        4,
        5
      ],
      "HBNHAKJHDJC": 6,
      "DBLDBAJDLBP": 7,
      "EOCOOJDFMLJ": 5
    },
    {
      "LGJCPENNFBC": 703,
      "OBDBAJHHNDI": 703,
      "OIGJHKMMBLD": 1,
      "PEFDOIHIIBG": 1,
      "BFBNEHIIGKB": [
        1,
        2,
        6
      ],
      "HBNHAKJHDJC": 10,
      "DBLDBAJDLBP": 7,
      "EOCOOJDFMLJ": 5
    },
    {
      "LGJCPENNFBC": 704,
      "OBDBAJHHNDI": 704,
      "OIGJHKMMBLD": 3,
      "PEFDOIHIIBG": 2,
      "BFBNEHIIGKB": [
        1,
        5,
        6
      ],
      "HBNHAKJHDJC": 4,
      "DBLDBAJDLBP": 7,
      "EOCOOJDFMLJ": 5
    },
    {
      "LGJCPENNFBC": 705,
      "OBDBAJHHNDI": 705,
      "OIGJHKMMBLD": 3,
      "PEFDOIHIIBG": 2,
      "BFBNEHIIGKB": [
        1,
        4,
        3
      ],
      "HBNHAKJHDJC": 6,
      "DBLDBAJDLBP": 7,
      "EOCOOJDFMLJ": 5
    },
    {
      "LGJCPENNFBC": 706,
      "OBDBAJHHNDI": 706,
      "OIGJHKMMBLD": 3,
      "PEFDOIHIIBG": 2,
      "BFBNEHIIGKB": [
        1,
        2,
        3
      ],
      "HBNHAKJHDJC": 13,
      "DBLDBAJDLBP": 8,
      "EOCOOJDFMLJ": 6
    },
    {
      "LGJCPENNFBC": 707,
      "OBDBAJHHNDI": 707,
      "OIGJHKMMBLD": 3,
      "PEFDOIHIIBG": 2,
      "BFBNEHIIGKB": [
        1,
        5,
        6
      ],
      "HBNHAKJHDJC": 13,
      "DBLDBAJDLBP": 8,
      "EOCOOJDFMLJ": 6
    },
    {
      "LGJCPENNFBC": 708,
      "OBDBAJHHNDI": 708,
      "OIGJHKMMBLD": 2,
      "PEFDOIHIIBG": 1,
      "BFBNEHIIGKB": [
        1,
        4,
        3
      ],
      "HBNHAKJHDJC": 2,
      "DBLDBAJDLBP": 8,
      "EOCOOJDFMLJ": 6
    },
    {
      "LGJCPENNFBC": 709,
      "OBDBAJHHNDI": 709,
      "OIGJHKMMBLD": 2,
      "PEFDOIHIIBG": 1,
      "BFBNEHIIGKB": [
        1,
        5,
        6
      ],
      "HBNHAKJHDJC": 6,
      "DBLDBAJDLBP": 8,
      "EOCOOJDFMLJ": 6
    },
    {
      "LGJCPENNFBC": 830,
      "OBDBAJHHNDI": 830,
      "OIGJHKMMBLD": 2,
      "PEFDOIHIIBG": 1,
      "BFBNEHIIGKB": [
        1,
        4,
        3
      ],
      "HBNHAKJHDJC": 11,
      "DBLDBAJDLBP": 9,
      "EOCOOJDFMLJ": 7
    },
    {
      "LGJCPENNFBC": 831,
      "OBDBAJHHNDI": 831,
      "OIGJHKMMBLD": 1,
      "PEFDOIHIIBG": 1,
      "BFBNEHIIGKB": [
        1,
        2,
        3
      ],
      "HBNHAKJHDJC": 1,
      "DBLDBAJDLBP": 7,
      "EOCOOJDFMLJ": 5
    },
    {
      "LGJCPENNFBC": 832,
      "OBDBAJHHNDI": 832,
      "OIGJHKMMBLD": 1,
      "PEFDOIHIIBG": 1,
      "BFBNEHIIGKB": [
        1,
        5,
        6
      ],
      "HBNHAKJHDJC": 2,
      "DBLDBAJDLBP": 7,
      "EOCOOJDFMLJ": 5
    },
    {
      "LGJCPENNFBC": 833,
      "OBDBAJHHNDI": 833,
      "OIGJHKMMBLD": 3,
      "PEFDOIHIIBG": 2,
      "BFBNEHIIGKB": [
        1,
        4,
        3
      ],
      "HBNHAKJHDJC": 5,
      "DBLDBAJDLBP": 7,
      "EOCOOJDFMLJ": 5
    },
    {
      "LGJCPENNFBC": 834,
      "OBDBAJHHNDI": 834,
      "OIGJHKMMBLD": 3,
      "PEFDOIHIIBG": 2,
      "BFBNEHIIGKB": [
        1,
        5,
        6
      ],
      "HBNHAKJHDJC": 4,
      "DBLDBAJDLBP": 7,
      "EOCOOJDFMLJ": 5
    },
    {
      "LGJCPENNFBC": 835,
      "OBDBAJHHNDI": 835,
      "OIGJHKMMBLD": 3,
      "PEFDOIHIIBG": 2,
      "BFBNEHIIGKB": [
        1,
        4,
        3
      ],
      "HBNHAKJHDJC": 6,
      "DBLDBAJDLBP": 7,
      "EOCOOJDFMLJ": 5
    },
    {
      "LGJCPENNFBC": 836,
      "OBDBAJHHNDI": 836,
      "OIGJHKMMBLD": 3,
      "PEFDOIHIIBG": 2,
      "BFBNEHIIGKB": [
        1,
        2,
        3
      ],
      "HBNHAKJHDJC": 12,
      "DBLDBAJDLBP": 8,
      "EOCOOJDFMLJ": 6
    },
    {
      "LGJCPENNFBC": 837,
      "OBDBAJHHNDI": 837,
      "OIGJHKMMBLD": 3,
      "PEFDOIHIIBG": 2,
      "BFBNEHIIGKB": [
        1,
        5,
        6
      ],
      "HBNHAKJHDJC": 1,
      "DBLDBAJDLBP": 8,
      "EOCOOJDFMLJ": 6
    },
    {
      "LGJCPENNFBC": 838,
      "OBDBAJHHNDI": 838,
      "OIGJHKMMBLD": 2,
      "PEFDOIHIIBG": 1,
      "BFBNEHIIGKB": [
        1,
        4,
        3
      ],
      "HBNHAKJHDJC": 2,
      "DBLDBAJDLBP": 8,
      "EOCOOJDFMLJ": 6
    },
    {
      "LGJCPENNFBC": 839,
      "OBDBAJHHNDI": 839,
      "OIGJHKMMBLD": 2,
      "PEFDOIHIIBG": 1,
      "BFBNEHIIGKB": [
        1,
        5,
        6
      ],
      "HBNHAKJHDJC": 5,
      "DBLDBAJDLBP": 8,
      "EOCOOJDFMLJ": 6
    }
  ]
}